{"contain":{"4022":{"path":"H022_output","img":"H022","skill":301,"actiontime":0.2,"speed":130,"skill_auto_script":"","next_skill":"S302_magic_H022_attack","skill_auto":0,"skill_script":"S301_magic_H022_attack","trail":1,"shadow":2,"hit_power":0,"id":4022,"atk_power":200,"hit_area":280,"skill_cancel_time":0.2,"width":100,"hit_rate":1.6,"name":"美杜莎","atk_script":"H022_normal_attack","height":210,"job":3,"bodytype":1.3,"hit_script":""},"3022":{"path":"M022_output","img":"M022","skill":0,"actiontime":0.1,"speed":180,"skill_auto_script":"","next_skill":"","skill_auto":0,"skill_script":"","trail":0,"shadow":1,"hit_power":0,"id":3022,"atk_power":250,"hit_area":40,"skill_cancel_time":0,"width":80,"hit_rate":1.45,"name":"羊頭人武士","atk_script":"M022_normal_attack","height":160,"job":2,"bodytype":1.3,"hit_script":"hit_11"},"4060":{"path":"H060_output","img":"H060","skill":0,"actiontime":0.2,"speed":190,"skill_auto_script":"","next_skill":"","skill_auto":0,"skill_script":"","trail":0,"shadow":1,"hit_power":0,"id":4060,"atk_power":200,"hit_area":40,"skill_cancel_time":0.2,"width":60,"hit_rate":1.45,"name":"黑暗精靈戰士","atk_script":"H060_normal_attack","height":190,"job":2,"bodytype":1.3,"hit_script":"hit_11"},"3060":{"path":"M060_output","img":"M060","skill":312,"actiontime":1,"speed":110,"skill_auto_script":"","next_skill":"S312_magic_M060_attack","skill_auto":0,"skill_script":"S221_magic_M059_attack","trail":0,"shadow":1,"hit_power":0,"id":3060,"atk_power":250,"hit_area":40,"skill_cancel_time":0,"width":100,"hit_rate":1.45,"name":"白銀塔羅斯","atk_script":"M060_normal_attack","height":180,"job":2,"bodytype":1.3,"hit_script":"hit_11"},"3004":{"path":"M004_output","img":"M004","skill":0,"actiontime":0.2,"speed":30,"skill_auto_script":"","next_skill":"","skill_auto":0,"skill_script":"","trail":0,"shadow":1,"hit_power":0,"id":3004,"atk_power":250,"hit_area":40,"skill_cancel_time":0,"width":50,"hit_rate":1.45,"name":"金色史萊姆","atk_script":"M004_normal_attack","height":90,"job":2,"bodytype":1.3,"hit_script":"hit_31"},"4004":{"path":"H004_output","img":"H004","skill":321,"actiontime":0.2,"speed":210,"skill_auto_script":"H004_auto1_attack","next_skill":"S322_magic_H004_attack","skill_auto":610,"skill_script":"S321_magic_H004_attack","trail":1,"shadow":1,"hit_power":0,"id":4004,"atk_power":200,"hit_area":290,"skill_cancel_time":0.2,"width":80,"hit_rate":1.6,"name":"阿波羅","atk_script":"H004_normal_attack","height":200,"job":3,"bodytype":1.3,"hit_script":"hit_31"},"4050":{"path":"H045_output","img":"H050","skill":0,"actiontime":0.2,"speed":220,"skill_auto_script":"","next_skill":"","skill_auto":0,"skill_script":"","trail":0,"shadow":1,"hit_power":0,"id":4050,"atk_power":200,"hit_area":20,"skill_cancel_time":0,"width":90,"hit_rate":1.8,"name":"希臘勇士","atk_script":"H045_normal_attack","height":210,"job":1,"bodytype":1.3,"hit_script":"hit_11"},"3098":{"path":"M098_output","img":"M098","skill":211,"actiontime":0.2,"speed":220,"skill_auto_script":"","next_skill":"S212_magic_M098_attack","skill_auto":0,"skill_script":"S211_magic_M098_attack","trail":0,"shadow":1,"hit_power":0,"id":3098,"atk_power":250,"hit_area":40,"skill_cancel_time":0.2,"width":60,"hit_rate":1.45,"name":"金色塞壬之王","atk_script":"M098_normal_attack","height":160,"job":2,"bodytype":1.3,"hit_script":"hit_11"},"4098":{"path":"H098_output","img":"H098","skill":0,"actiontime":1,"speed":160,"skill_auto_script":"","next_skill":"","skill_auto":0,"skill_script":"","trail":0,"shadow":1,"hit_power":0,"id":4098,"atk_power":200,"hit_area":270,"skill_cancel_time":0,"width":120,"hit_rate":1.6,"name":"人馬射手","atk_script":"H098_normal_attack","height":230,"job":3,"bodytype":1.3,"hit_script":"hit_11"},"3050":{"path":"M050_output","img":"M050","skill":0,"actiontime":1,"speed":220,"skill_auto_script":"","next_skill":"","skill_auto":0,"skill_script":"","trail":0,"shadow":1,"hit_power":0,"id":3050,"atk_power":250,"hit_area":280,"skill_cancel_time":0,"width":60,"hit_rate":1.65,"name":"噴火蝙蝠王","atk_script":"M050_normal_attack","height":200,"job":2,"bodytype":1.3,"hit_script":"hit_11"},"4078":{"path":"H078_output","img":"H078","skill":301,"actiontime":1,"speed":210,"skill_auto_script":"H078_auto1_attack","next_skill":"S302_magic_H078_attack","skill_auto":608,"skill_script":"S301_magic_H078_attack","trail":0,"shadow":1,"hit_power":0,"id":4078,"atk_power":200,"hit_area":280,"skill_cancel_time":0,"width":80,"hit_rate":1.6,"name":"阿爾忒彌斯","atk_script":"H078_normal_attack","height":210,"job":3,"bodytype":1.3,"hit_script":"hit_11"},"3078":{"path":"M078_output","img":"M078","skill":0,"actiontime":1,"speed":220,"skill_auto_script":"","next_skill":"","skill_auto":0,"skill_script":"","trail":0,"shadow":1,"hit_power":0,"id":3078,"atk_power":250,"hit_area":40,"skill_cancel_time":0,"width":80,"hit_rate":1.45,"name":"遠古守護者","atk_script":"M078_normal_attack","height":200,"job":2,"bodytype":1.3,"hit_script":"hit_11"},"4011":{"path":"H011_output","img":"H011","skill":0,"actiontime":0.2,"speed":100,"skill_auto_script":"","next_skill":"","skill_auto":0,"skill_script":"","trail":0,"shadow":2,"hit_power":0,"id":4011,"atk_power":200,"hit_area":40,"skill_cancel_time":0,"width":120,"hit_rate":1.45,"name":"狂戰士","atk_script":"H011_normal_attack","height":190,"job":2,"bodytype":1.3,"hit_script":"hit_11"},"3103":{"path":"M100_output","img":"M100","skill":402,"actiontime":0.1,"speed":190,"skill_auto_script":"","next_skill":"S402_magic_M100_attack","skill_auto":0,"skill_script":"S402_magic_M100_attack","trail":0,"shadow":3,"hit_power":0,"id":3103,"atk_power":250,"hit_area":80,"skill_cancel_time":0.1,"width":350,"hit_rate":1.45,"name":"上古凶神","atk_script":"M100_normal_attack","height":250,"job":2,"bodytype":1.1,"hit_script":""},"3026":{"path":"M026_output","img":"M026","skill":401,"actiontime":0.1,"speed":160,"skill_auto_script":"","next_skill":"S402_magic_M026_attack","skill_auto":0,"skill_script":"S401_magic_M026_attack","trail":1,"shadow":2,"hit_power":0,"id":3026,"atk_power":250,"hit_area":280,"skill_cancel_time":0.1,"width":70,"hit_rate":1.65,"name":"黑龍","atk_script":"M026_normal_attack","height":250,"job":4,"bodytype":0.9,"hit_script":"hit_41"},"4026":{"path":"H026_output","img":"H026","skill":0,"actiontime":0.1,"speed":160,"skill_auto_script":"","next_skill":"","skill_auto":0,"skill_script":"","trail":0,"shadow":2,"hit_power":0,"id":4026,"atk_power":200,"hit_area":40,"skill_cancel_time":0,"width":100,"hit_rate":1.45,"name":"蛇妖執法者","atk_script":"H026_normal_attack","height":210,"job":2,"bodytype":1.3,"hit_script":"hit_11"},"3031":{"path":"M031_output","img":"M031","skill":0,"actiontime":0.2,"speed":220,"skill_auto_script":"","next_skill":"","skill_auto":0,"skill_script":"","trail":0,"shadow":1,"hit_power":0,"id":3031,"atk_power":250,"hit_area":40,"skill_cancel_time":0,"width":100,"hit_rate":1.45,"name":"小黑龍","atk_script":"M031_normal_attack","height":190,"job":2,"bodytype":1.3,"hit_script":"hit_42"},"3071":{"path":"M071_output","img":"M071","skill":0,"actiontime":1,"speed":80,"skill_auto_script":"","next_skill":"","skill_auto":0,"skill_script":"","trail":0,"shadow":1,"hit_power":0,"id":3071,"atk_power":250,"hit_area":50,"skill_cancel_time":0,"width":120,"hit_rate":1.8,"name":"獨眼巨人衛士","atk_script":"M071_normal_attack","height":240,"job":1,"bodytype":1.3,"hit_script":"hit_11"},"4071":{"path":"H071_output","img":"H071","skill":0,"actiontime":0.2,"speed":200,"skill_auto_script":"","next_skill":"","skill_auto":0,"skill_script":"","trail":0,"shadow":1,"hit_power":0,"id":4071,"atk_power":200,"hit_area":40,"skill_cancel_time":0,"width":60,"hit_rate":1.45,"name":"深火氏族戰士","atk_script":"H071_normal_attack","height":150,"job":2,"bodytype":1.3,"hit_script":"hit_11"},"3021":{"path":"M021_output","img":"M021","skill":201,"actiontime":0.1,"speed":200,"skill_auto_script":"","next_skill":"S202_magic_M021_attack","skill_auto":0,"skill_script":"S201_magic_M021_attack","trail":0,"shadow":1,"hit_power":0,"id":3021,"atk_power":250,"hit_area":50,"skill_cancel_time":0.1,"width":80,"hit_rate":1.45,"name":"牧神潘","atk_script":"M021_normal_attack","height":160,"job":2,"bodytype":1.5,"hit_script":"hit_11"},"3077":{"path":"M077_output","img":"M077","skill":0,"actiontime":1,"speed":220,"skill_auto_script":"","next_skill":"","skill_auto":0,"skill_script":"","trail":0,"shadow":1,"hit_power":0,"id":3077,"atk_power":250,"hit_area":40,"skill_cancel_time":0,"width":80,"hit_rate":1.45,"name":"智慧之樹","atk_script":"M077_normal_attack","height":200,"job":2,"bodytype":1.3,"hit_script":"hit_11"},"4031":{"path":"H031_output","img":"H031","skill":0,"actiontime":0.2,"speed":140,"skill_auto_script":"","next_skill":"","skill_auto":0,"skill_script":"","trail":1,"shadow":2,"hit_power":0,"id":4031,"atk_power":200,"hit_area":250,"skill_cancel_time":0,"width":120,"hit_rate":1.6,"name":"森林復仇者","atk_script":"H031_normal_attack","height":210,"job":3,"bodytype":1.3,"hit_script":"hit_31"},"3041":{"path":"M041_output","img":"M041","skill":0,"actiontime":1,"speed":220,"skill_auto_script":"","next_skill":"","skill_auto":0,"skill_script":"","trail":0,"shadow":1,"hit_power":0,"id":3041,"atk_power":250,"hit_area":40,"skill_cancel_time":0,"width":60,"hit_rate":1.45,"name":"彩色鷹身女妖之王","atk_script":"M041_normal_attack","height":200,"job":2,"bodytype":1.3,"hit_script":"hit_11"},"3013":{"path":"M013_output","img":"M013","skill":402,"actiontime":0.1,"speed":150,"skill_auto_script":"","next_skill":"S402_magic_M013_attack","skill_auto":0,"skill_script":"S402_magic_M013_attack","trail":0,"shadow":3,"hit_power":0,"id":3013,"atk_power":250,"hit_area":120,"skill_cancel_time":0.1,"width":440,"hit_rate":1.45,"name":"詛咒巨蟒拉冬","atk_script":"M013_normal_attack","height":300,"job":2,"bodytype":1.1,"hit_script":""},"4013":{"path":"H013_output","img":"H013","skill":321,"actiontime":0.3,"speed":140,"skill_auto_script":"H013_auto1_attack","next_skill":"S322_magic_H013_attack","skill_auto":606,"skill_script":"S321_magic_H013_attack","trail":1,"shadow":1,"hit_power":0,"id":4013,"atk_power":200,"hit_area":280,"skill_cancel_time":0.1,"width":100,"hit_rate":1.6,"name":"芙蕾","atk_script":"H013_normal_attack","height":180,"job":3,"bodytype":1.3,"hit_script":"hit_31"},"3011":{"path":"M011_output","img":"M011","skill":0,"actiontime":0.1,"speed":220,"skill_auto_script":"","next_skill":"","skill_auto":0,"skill_script":"","trail":0,"shadow":1,"hit_power":0,"id":3011,"atk_power":250,"hit_area":40,"skill_cancel_time":0,"width":100,"hit_rate":1.45,"name":"火鳳凰","atk_script":"M011_normal_attack","height":230,"job":2,"bodytype":1.3,"hit_script":""},"4041":{"path":"H041_output","img":"H041","skill":0,"actiontime":0.2,"speed":180,"skill_auto_script":"","next_skill":"","skill_auto":0,"skill_script":"","trail":1,"shadow":1,"hit_power":0,"id":4041,"atk_power":200,"hit_area":260,"skill_cancel_time":0.2,"width":80,"hit_rate":1.6,"name":"希臘神射手","atk_script":"H041_normal_attack","height":240,"job":3,"bodytype":1.3,"hit_script":"hit_31"},"3073":{"path":"M073_output","img":"M073","skill":222,"actiontime":1,"speed":220,"skill_auto_script":"","next_skill":"S223_magic_M073_attack","skill_auto":0,"skill_script":"S222_magic_M073_attack","trail":0,"shadow":1,"hit_power":0,"id":3073,"atk_power":250,"hit_area":40,"skill_cancel_time":0,"width":80,"hit_rate":1.45,"name":"百臂巨人","atk_script":"M073_normal_attack","height":200,"job":2,"bodytype":1.3,"hit_script":"hit_11"},"3080":{"path":"M080_output","img":"M080","skill":0,"actiontime":1,"speed":220,"skill_auto_script":"","next_skill":"","skill_auto":0,"skill_script":"","trail":0,"shadow":1,"hit_power":0,"id":3080,"atk_power":250,"hit_area":40,"skill_cancel_time":0,"width":80,"hit_rate":1.45,"name":"冰霜巨人之王","atk_script":"M080_normal_attack","height":200,"job":2,"bodytype":1.3,"hit_script":"hit_11"},"3069":{"path":"M069_output","img":"M069","skill":0,"actiontime":1,"speed":220,"skill_auto_script":"","next_skill":"","skill_auto":0,"skill_script":"","trail":0,"shadow":1,"hit_power":0,"id":3069,"atk_power":250,"hit_area":40,"skill_cancel_time":0,"width":80,"hit_rate":1.45,"name":"高級牛頭人錘兵","atk_script":"M069_normal_attack","height":200,"job":2,"bodytype":1.3,"hit_script":"hit_11"},"3040":{"path":"M040_output","img":"M040","skill":0,"actiontime":0.1,"speed":220,"skill_auto_script":"","next_skill":"","skill_auto":0,"skill_script":"","trail":0,"shadow":1,"hit_power":0,"id":3040,"atk_power":250,"hit_area":40,"skill_cancel_time":0,"width":60,"hit_rate":1.45,"name":"綠羽鷹身女妖之王","atk_script":"M040_normal_attack","height":200,"job":2,"bodytype":1.3,"hit_script":"hit_11"},"4043":{"path":"H043_output","img":"H043","skill":0,"actiontime":0.2,"speed":180,"skill_auto_script":"","next_skill":"","skill_auto":0,"skill_script":"","trail":1,"shadow":1,"hit_power":0,"id":4043,"atk_power":200,"hit_area":260,"skill_cancel_time":0,"width":80,"hit_rate":1.6,"name":"特洛伊神射手","atk_script":"H043_normal_attack","height":210,"job":3,"bodytype":1.3,"hit_script":"hit_31"},"4040":{"path":"H040_output","img":"H040","skill":0,"actiontime":0.2,"speed":180,"skill_auto_script":"","next_skill":"","skill_auto":0,"skill_script":"","trail":1,"shadow":1,"hit_power":0,"id":4040,"atk_power":200,"hit_area":260,"skill_cancel_time":0,"width":80,"hit_rate":1.6,"name":"希臘弓兵","atk_script":"H040_normal_attack","height":220,"job":3,"bodytype":1.3,"hit_script":"hit_31"},"3052":{"path":"M052_output","img":"M052","skill":0,"actiontime":1,"speed":220,"skill_auto_script":"","next_skill":"","skill_auto":0,"skill_script":"","trail":0,"shadow":1,"hit_power":0,"id":3052,"atk_power":250,"hit_area":40,"skill_cancel_time":0,"width":60,"hit_rate":1.45,"name":"奇美拉","atk_script":"M052_normal_attack","height":200,"job":2,"bodytype":1.3,"hit_script":"hit_11"},"4052":{"path":"H047_output","img":"H052","skill":0,"actiontime":0.2,"speed":180,"skill_auto_script":"","next_skill":"","skill_auto":0,"skill_script":"","trail":0,"shadow":1,"hit_power":0,"id":4052,"atk_power":200,"hit_area":20,"skill_cancel_time":0,"width":80,"hit_rate":1.8,"name":"特洛伊勇士","atk_script":"H052_normal_attack","height":210,"job":1,"bodytype":1.3,"hit_script":"hit_11"},"3070":{"path":"M070_output","img":"M070","skill":0,"actiontime":1,"speed":80,"skill_auto_script":"","next_skill":"","skill_auto":0,"skill_script":"","trail":0,"shadow":1,"hit_power":0,"id":3070,"atk_power":250,"hit_area":50,"skill_cancel_time":0,"width":120,"hit_rate":1.8,"name":"獨眼巨人之王","atk_script":"M070_normal_attack","height":240,"job":1,"bodytype":1.3,"hit_script":"hit_11"},"4100":{"path":"H100_output","img":"H100","skill":211,"actiontime":1,"speed":180,"skill_auto_script":"H100_auto1_attack","next_skill":"S212_magic_H100_attack","skill_auto":608,"skill_script":"S211_magic_H100_attack","trail":0,"shadow":1,"hit_power":0,"id":4100,"atk_power":200,"hit_area":40,"skill_cancel_time":0,"width":80,"hit_rate":1.45,"name":"亞馬遜女王","atk_script":"H100_normal_attack","height":210,"job":2,"bodytype":1.3,"hit_script":"hit_11"},"3100":{"path":"M100_output","img":"M100","skill":402,"actiontime":0.1,"speed":190,"skill_auto_script":"","next_skill":"S402_magic_M100_attack","skill_auto":0,"skill_script":"S402_magic_M100_attack","trail":0,"shadow":3,"hit_power":0,"id":3100,"atk_power":250,"hit_area":80,"skill_cancel_time":0.1,"width":350,"hit_rate":1.45,"name":"地獄九頭蛇","atk_script":"M100_normal_attack","height":250,"job":2,"bodytype":1.1,"hit_script":""},"4042":{"path":"H042_output","img":"H042","skill":0,"actiontime":0.2,"speed":180,"skill_auto_script":"","next_skill":"","skill_auto":0,"skill_script":"","trail":1,"shadow":1,"hit_power":0,"id":4042,"atk_power":200,"hit_area":260,"skill_cancel_time":0,"width":80,"hit_rate":1.6,"name":"特洛伊弓兵","atk_script":"H042_normal_attack","height":200,"job":3,"bodytype":1.3,"hit_script":"hit_31"},"3042":{"path":"M042_output","img":"M042","skill":0,"actiontime":0.1,"speed":220,"skill_auto_script":"","next_skill":"","skill_auto":0,"skill_script":"","trail":0,"shadow":1,"hit_power":0,"id":3042,"atk_power":250,"hit_area":40,"skill_cancel_time":0,"width":50,"hit_rate":1.45,"name":"石像鬼","atk_script":"M042_normal_attack","height":200,"job":2,"bodytype":1.3,"hit_script":"hit_11"},"3034":{"path":"M034_output","img":"M034","skill":0,"actiontime":0.2,"speed":220,"skill_auto_script":"","next_skill":"","skill_auto":0,"skill_script":"","trail":0,"shadow":1,"hit_power":0,"id":3034,"atk_power":250,"hit_area":40,"skill_cancel_time":0,"width":60,"hit_rate":1.45,"name":"小金龍","atk_script":"M034_normal_attack","height":190,"job":2,"bodytype":1.3,"hit_script":"hit_11"},"3082":{"path":"M082_output","img":"M082","skill":0,"actiontime":1,"speed":220,"skill_auto_script":"","next_skill":"","skill_auto":0,"skill_script":"","trail":0,"shadow":1,"hit_power":0,"id":3082,"atk_power":250,"hit_area":40,"skill_cancel_time":0,"width":80,"hit_rate":1.45,"name":"石巨人之王","atk_script":"M082_normal_attack","height":200,"job":2,"bodytype":1.3,"hit_script":"hit_11"},"4082":{"path":"H082_output","img":"H082","skill":411,"actiontime":1,"speed":140,"skill_auto_script":"H082_auto1_attack","next_skill":"S412_magic_H082_attack","skill_auto":601,"skill_script":"S411_magic_H082_attack","trail":0,"shadow":1,"hit_power":0,"id":4082,"atk_power":200,"hit_area":210,"skill_cancel_time":0,"width":90,"hit_rate":1.65,"name":"俄耳甫斯","atk_script":"H082_normal_attack","height":190,"job":4,"bodytype":1.3,"hit_script":"hit_11"},"3063":{"path":"M063_output","img":"M063","skill":0,"actiontime":1,"speed":220,"skill_auto_script":"","next_skill":"","skill_auto":0,"skill_script":"","trail":0,"shadow":1,"hit_power":0,"id":3063,"atk_power":250,"hit_area":40,"skill_cancel_time":0,"width":80,"hit_rate":1.45,"name":"青銅塔羅斯","atk_script":"M063_normal_attack","height":160,"job":2,"bodytype":1.3,"hit_script":"hit_11"},"4063":{"path":"H063_output","img":"H063","skill":0,"actiontime":0.3,"speed":200,"skill_auto_script":"","next_skill":"","skill_auto":0,"skill_script":"","trail":1,"shadow":1,"hit_power":0,"id":4063,"atk_power":200,"hit_area":240,"skill_cancel_time":0.3,"width":80,"hit_rate":1.65,"name":"黑暗精靈法師","atk_script":"H063_normal_attack","height":190,"job":4,"bodytype":1.3,"hit_script":"hit_42"},"3085":{"path":"M085_output","img":"M085","skill":0,"actiontime":1,"speed":220,"skill_auto_script":"","next_skill":"","skill_auto":0,"skill_script":"","trail":0,"shadow":1,"hit_power":0,"id":3085,"atk_power":250,"hit_area":60,"skill_cancel_time":0,"width":60,"hit_rate":1.45,"name":"小火巨人","atk_script":"M085_normal_attack","height":160,"job":2,"bodytype":1.3,"hit_script":"hit_31"},"3083":{"path":"M083_output","img":"M083","skill":402,"actiontime":1,"speed":220,"skill_auto_script":"","next_skill":"S402_magic_M083_attack","skill_auto":0,"skill_script":"S402_magic_M083_attack","trail":0,"shadow":1,"hit_power":0,"id":3083,"atk_power":250,"hit_area":40,"skill_cancel_time":0,"width":80,"hit_rate":1.45,"name":"雷電巨人之王","atk_script":"M083_normal_attack","height":200,"job":2,"bodytype":1.3,"hit_script":"hit_11"},"3016":{"path":"M016_output","img":"M016","skill":0,"actiontime":1,"speed":220,"skill_auto_script":"","next_skill":"","skill_auto":0,"skill_script":"","trail":0,"shadow":3,"hit_power":0,"id":3016,"atk_power":250,"hit_area":40,"skill_cancel_time":0,"width":150,"hit_rate":1.8,"name":"耶夢加得","atk_script":"M016_normal_attack","height":250,"job":2,"bodytype":1.2,"hit_script":""},"3102":{"path":"M100_output","img":"M100","skill":402,"actiontime":0.1,"speed":190,"skill_auto_script":"","next_skill":"S402_magic_M100_attack","skill_auto":0,"skill_script":"S402_magic_M100_attack","trail":0,"shadow":3,"hit_power":0,"id":3102,"atk_power":250,"hit_area":80,"skill_cancel_time":0.1,"width":350,"hit_rate":1.45,"name":"八岐大蛇","atk_script":"M100_normal_attack","height":250,"job":2,"bodytype":1.1,"hit_script":""},"3038":{"path":"M038_output","img":"M038","skill":0,"actiontime":0.1,"speed":180,"skill_auto_script":"","next_skill":"","skill_auto":0,"skill_script":"","trail":0,"shadow":1,"hit_power":0,"id":3038,"atk_power":250,"hit_area":40,"skill_cancel_time":0,"width":80,"hit_rate":1.45,"name":"黑羽鷹身女妖","atk_script":"M038_normal_attack","height":220,"job":2,"bodytype":1.3,"hit_script":"hit_11"},"4038":{"path":"H038_output","img":"H038","skill":301,"actiontime":0.4,"speed":150,"skill_auto_script":"H038_normal_attack","next_skill":"S302_magic_H038_attack","skill_auto":605,"skill_script":"S301_magic_H038_attack","trail":1,"shadow":1,"hit_power":0,"id":4038,"atk_power":200,"hit_area":270,"skill_cancel_time":0.5,"width":100,"hit_rate":1.6,"name":"阿伽門農","atk_script":"H038_normal_attack","height":210,"job":3,"bodytype":1.3,"hit_script":"hit_31"},"3001":{"path":"M001_output","img":"M001","skill":0,"actiontime":0.2,"speed":30,"skill_auto_script":"","next_skill":"","skill_auto":0,"skill_script":"","trail":0,"shadow":1,"hit_power":0,"id":3001,"atk_power":250,"hit_area":40,"skill_cancel_time":0,"width":50,"hit_rate":1.45,"name":"綠色史萊姆","atk_script":"M001_normal_attack","height":90,"job":2,"bodytype":1.3,"hit_script":"hit_31"},"3047":{"path":"M047_output","img":"M047","skill":0,"actiontime":0.2,"speed":220,"skill_auto_script":"","next_skill":"","skill_auto":0,"skill_script":"","trail":0,"shadow":1,"hit_power":0,"id":3047,"atk_power":250,"hit_area":280,"skill_cancel_time":0,"width":40,"hit_rate":1.65,"name":"紅色噴火蝙蝠","atk_script":"M047_normal_attack","height":200,"job":2,"bodytype":1.3,"hit_script":"hit_11"},"3048":{"path":"M045_output","img":"M048","skill":0,"actiontime":0.2,"speed":220,"skill_auto_script":"","next_skill":"","skill_auto":0,"skill_script":"","trail":1,"shadow":1,"hit_power":0,"id":3048,"atk_power":250,"hit_area":280,"skill_cancel_time":0,"width":40,"hit_rate":1.65,"name":"黑色噴火蝙蝠","atk_script":"M048_normal_attack","height":200,"job":4,"bodytype":1.3,"hit_script":"hit_11"},"4036":{"path":"H036_output","img":"H036","skill":221,"actiontime":0.2,"speed":110,"skill_auto_script":"","next_skill":"S222_magic_attack","skill_auto":0,"skill_script":"S221_magic_attack","trail":0,"shadow":2,"hit_power":0,"id":4036,"atk_power":200,"hit_area":40,"skill_cancel_time":0.2,"width":140,"hit_rate":1.45,"name":"達提斯","atk_script":"H036_normal_attack","height":230,"job":2,"bodytype":1.3,"hit_script":"hit_11"},"3036":{"path":"M036_output","img":"M036","skill":0,"actiontime":1,"speed":220,"skill_auto_script":"","next_skill":"","skill_auto":0,"skill_script":"","trail":0,"shadow":1,"hit_power":0,"id":3036,"atk_power":250,"hit_area":40,"skill_cancel_time":0,"width":60,"hit_rate":1.45,"name":"綠羽鷹身女妖","atk_script":"M036_normal_attack","height":200,"job":2,"bodytype":1.3,"hit_script":"hit_11"},"4087":{"path":"H087_output","img":"H087","skill":201,"actiontime":1,"speed":200,"skill_auto_script":"H087_auto1_attack","next_skill":"S202_magic_H087_attack","skill_auto":601,"skill_script":"S201_magic_H087_attack","trail":0,"shadow":1,"hit_power":0,"id":4087,"atk_power":200,"hit_area":40,"skill_cancel_time":0,"width":80,"hit_rate":1.45,"name":"俄狄浦斯王","atk_script":"H087_normal_attack","height":180,"job":2,"bodytype":1.3,"hit_script":"hit_11"},"3087":{"path":"M087_output","img":"M087","skill":0,"actiontime":1,"speed":220,"skill_auto_script":"","next_skill":"","skill_auto":0,"skill_script":"","trail":0,"shadow":1,"hit_power":0,"id":3087,"atk_power":250,"hit_area":40,"skill_cancel_time":0,"width":60,"hit_rate":1.45,"name":"小雷電巨人","atk_script":"M087_normal_attack","height":160,"job":2,"bodytype":1.3,"hit_script":"hit_11"},"3037":{"path":"M037_output","img":"M037","skill":0,"actiontime":1,"speed":220,"skill_auto_script":"","next_skill":"","skill_auto":0,"skill_script":"","trail":0,"shadow":1,"hit_power":0,"id":3037,"atk_power":250,"hit_area":40,"skill_cancel_time":0,"width":60,"hit_rate":1.45,"name":"褐羽鷹身女妖","atk_script":"M037_normal_attack","height":200,"job":2,"bodytype":1.3,"hit_script":"hit_11"},"3023":{"path":"M022_output","img":"M023","skill":0,"actiontime":0.1,"speed":180,"skill_auto_script":"","next_skill":"","skill_auto":0,"skill_script":"","trail":0,"shadow":1,"hit_power":0,"id":3023,"atk_power":250,"hit_area":40,"skill_cancel_time":0,"width":100,"hit_rate":1.45,"name":"羊頭人戰士","atk_script":"M023_normal_attack","height":160,"job":2,"bodytype":1.3,"hit_script":"hit_11"},"4037":{"path":"H037_output","img":"H037","skill":301,"actiontime":0.3,"speed":110,"skill_auto_script":"","next_skill":"S302_magic_H037_attack","skill_auto":0,"skill_script":"S301_magic_H037_attack","trail":1,"shadow":2,"hit_power":0,"id":4037,"atk_power":200,"hit_area":270,"skill_cancel_time":0.2,"width":100,"hit_rate":1.6,"name":"薛西斯","atk_script":"H037_normal_attack","height":230,"job":3,"bodytype":1.3,"hit_script":"hit_31"},"5018":{"path":"M018_output","img":"M018","skill":0,"actiontime":0.1,"speed":33,"skill_auto_script":"","next_skill":"","skill_auto":0,"skill_script":"","trail":0,"shadow":2,"hit_power":0,"id":5018,"atk_power":200,"hit_area":50,"skill_cancel_time":0.1,"width":140,"hit_rate":1.8,"name":"山嶺食人妖","atk_script":"M018_normal_attack","height":240,"job":1,"bodytype":1.3,"hit_script":"hit_11"},"4091":{"path":"H091_output","img":"H091","skill":0,"actiontime":1,"speed":220,"skill_auto_script":"","next_skill":"","skill_auto":0,"skill_script":"","trail":0,"shadow":1,"hit_power":0,"id":4091,"atk_power":200,"hit_area":240,"skill_cancel_time":0,"width":60,"hit_rate":1.45,"name":"冥後侍女","atk_script":"H091_normal_attack","height":150,"job":2,"bodytype":1.3,"hit_script":"hit_11"},"4111":{"path":"H111_output","img":"H111","skill":301,"actiontime":0.3,"speed":190,"skill_auto_script":"H111_normal_attack","next_skill":"S302_magic_H111_attack","skill_auto":617,"skill_script":"S301_magic_H111_attack","trail":0,"shadow":1,"hit_power":0,"id":4111,"atk_power":200,"hit_area":280,"skill_cancel_time":0.3,"width":90,"hit_rate":1.6,"name":"萊戈拉斯","atk_script":"H111_normal_attack","height":180,"job":3,"bodytype":1.3,"hit_script":"hit_31"},"4017":{"path":"H017_output","img":"H017","skill":301,"actiontime":0.4,"speed":180,"skill_auto_script":"H017_normal_attack","next_skill":"S302_magic_H017_attack","skill_auto":601,"skill_script":"S301_magic_H017_attack","trail":1,"shadow":1,"hit_power":0,"id":4017,"atk_power":200,"hit_area":260,"skill_cancel_time":0.8,"width":100,"hit_rate":1.6,"name":"斯露德","atk_script":"H017_normal_attack","height":190,"job":3,"bodytype":1.3,"hit_script":"hit_31"},"4109":{"path":"H109_output","img":"H109","skill":201,"actiontime":0.3,"speed":200,"skill_auto_script":"H109_auto1_attack","next_skill":"S202_magic_H109_attack","skill_auto":601,"skill_script":"S201_magic_H109_attack","trail":0,"shadow":1,"hit_power":0,"id":4109,"atk_power":200,"hit_area":40,"skill_cancel_time":0.3,"width":80,"hit_rate":1.45,"name":"亞瑟王","atk_script":"H109_normal_attack","height":160,"job":2,"bodytype":1.3,"hit_script":"hit_11"},"3018":{"path":"M018_output","img":"M018","skill":221,"actiontime":0.1,"speed":33,"skill_auto_script":"","next_skill":"S222_magic_M018_attack","skill_auto":0,"skill_script":"S221_magic_M018_attack","trail":0,"shadow":2,"hit_power":0,"id":3018,"atk_power":250,"hit_area":40,"skill_cancel_time":0.1,"width":140,"hit_rate":1.8,"name":"山領食人妖","atk_script":"M018_normal_attack","height":240,"job":1,"bodytype":1.3,"hit_script":"hit_11"},"4035":{"path":"H033_output","img":"H035","skill":0,"actiontime":0.2,"speed":120,"skill_auto_script":"","next_skill":"","skill_auto":0,"skill_script":"","trail":1,"shadow":2,"hit_power":0,"id":4035,"atk_power":200,"hit_area":260,"skill_cancel_time":0,"width":120,"hit_rate":1.6,"name":"波斯神射手","atk_script":"H035_normal_attack","height":230,"job":3,"bodytype":1.3,"hit_script":"hit_11"},"3062":{"path":"M062_output","img":"M062","skill":0,"actiontime":1,"speed":220,"skill_auto_script":"","next_skill":"","skill_auto":0,"skill_script":"","trail":0,"shadow":1,"hit_power":0,"id":3062,"atk_power":250,"hit_area":40,"skill_cancel_time":0,"width":80,"hit_rate":1.45,"name":"鋼鐵塔羅斯","atk_script":"M062_normal_attack","height":160,"job":2,"bodytype":1.3,"hit_script":"hit_11"},"4106":{"path":"H106_output","img":"H106","skill":401,"actiontime":0.3,"speed":140,"skill_auto_script":"H106_auto1_attack","next_skill":"S402_magic_H106_attack","skill_auto":613,"skill_script":"S401_magic_H106_attack","trail":0,"shadow":1,"hit_power":0,"id":4106,"atk_power":200,"hit_area":240,"skill_cancel_time":0.3,"width":80,"hit_rate":1.65,"name":"海倫","atk_script":"H106_normal_attack","height":180,"job":4,"bodytype":1.3,"hit_script":"hit_41"},"4105":{"path":"H105_output","img":"H105","skill":301,"actiontime":0.3,"speed":210,"skill_auto_script":"H105_auto1_attack","next_skill":"S302_magic_H105_attack","skill_auto":611,"skill_script":"S301_magic_H105_attack","trail":1,"shadow":1,"hit_power":0,"id":4105,"atk_power":200,"hit_area":280,"skill_cancel_time":0.3,"width":80,"hit_rate":1.6,"name":"潘朵拉","atk_script":"H105_normal_attack","height":200,"job":3,"bodytype":1.3,"hit_script":"hit_31"},"4062":{"path":"H062_output","img":"H062","skill":0,"actiontime":0.2,"speed":200,"skill_auto_script":"","next_skill":"","skill_auto":0,"skill_script":"","trail":1,"shadow":1,"hit_power":0,"id":4062,"atk_power":200,"hit_area":240,"skill_cancel_time":0,"width":80,"hit_rate":1.65,"name":"精靈法師","atk_script":"H062_normal_attack","height":190,"job":4,"bodytype":1.3,"hit_script":"hit_42"},"3002":{"path":"M002_output","img":"M002","skill":0,"actiontime":0.2,"speed":30,"skill_auto_script":"","next_skill":"","skill_auto":0,"skill_script":"","trail":0,"shadow":1,"hit_power":0,"id":3002,"atk_power":250,"hit_area":40,"skill_cancel_time":0,"width":50,"hit_rate":1.45,"name":"紅色史萊姆","atk_script":"M002_normal_attack","height":90,"job":2,"bodytype":1.3,"hit_script":"hit_31"},"3029":{"path":"M029_output","img":"M029","skill":422,"actiontime":0.1,"speed":160,"skill_auto_script":"","next_skill":"S422_magic_M029_attack","skill_auto":0,"skill_script":"S422_magic_M029_attack","trail":1,"shadow":2,"hit_power":0,"id":3029,"atk_power":250,"hit_area":280,"skill_cancel_time":0.1,"width":70,"hit_rate":1.65,"name":"金龍","atk_script":"M029_normal_attack","height":250,"job":4,"bodytype":0.9,"hit_script":"hit_43"},"4029":{"path":"H029_output","img":"H029","skill":0,"actiontime":0.2,"speed":160,"skill_auto_script":"","next_skill":"","skill_auto":0,"skill_script":"","trail":1,"shadow":2,"hit_power":0,"id":4029,"atk_power":200,"hit_area":190,"skill_cancel_time":0,"width":90,"hit_rate":1.65,"name":"蛇妖施法者","atk_script":"H029_normal_attack","height":210,"job":4,"bodytype":1.3,"hit_script":"hit_42"},"4099":{"path":"H099_output","img":"H099","skill":0,"actiontime":1,"speed":160,"skill_auto_script":"","next_skill":"","skill_auto":0,"skill_script":"","trail":0,"shadow":1,"hit_power":0,"id":4099,"atk_power":200,"hit_area":270,"skill_cancel_time":0,"width":120,"hit_rate":1.6,"name":"人馬無雙射手","atk_script":"H099_normal_attack","height":230,"job":3,"bodytype":1.3,"hit_script":"hit_11"},"4103":{"path":"H103_output","img":"H103","skill":301,"actiontime":0.3,"speed":200,"skill_auto_script":"H103_auto1_attack","next_skill":"S302_magic_H103_attack","skill_auto":604,"skill_script":"S301_magic_H103_attack","trail":1,"shadow":1,"hit_power":0,"id":4103,"atk_power":200,"hit_area":280,"skill_cancel_time":0.3,"width":60,"hit_rate":1.6,"name":"火熱丘比特","atk_script":"H103_normal_attack","height":170,"job":3,"bodytype":1.3,"hit_script":"hit_31"},"4012":{"path":"H012_output","img":"H012","skill":311,"actiontime":0.1,"speed":180,"skill_auto_script":"H012_auto1_attack","next_skill":"S312_magic_H012_attack","skill_auto":602,"skill_script":"S311_magic_H012_attack","trail":1,"shadow":2,"hit_power":0,"id":4012,"atk_power":200,"hit_area":290,"skill_cancel_time":0.2,"width":120,"hit_rate":1.6,"name":"奧丁","atk_script":"H012_normal_attack","height":240,"job":3,"bodytype":1.3,"hit_script":"hit_31"},"3012":{"path":"M012_output","img":"M012","skill":0,"actiontime":0.1,"speed":220,"skill_auto_script":"","next_skill":"","skill_auto":0,"skill_script":"","trail":0,"shadow":1,"hit_power":0,"id":3012,"atk_power":250,"hit_area":40,"skill_cancel_time":0,"width":100,"hit_rate":1.45,"name":"孔雀","atk_script":"M012_normal_attack","height":230,"job":2,"bodytype":1.3,"hit_script":""},"4102":{"path":"H102_output","img":"H102","skill":301,"actiontime":1,"speed":150,"skill_auto_script":"H102_normal_attack","next_skill":"S302_magic_H102_attack","skill_auto":617,"skill_script":"S301_magic_H102_attack","trail":0,"shadow":1,"hit_power":0,"id":4102,"atk_power":200,"hit_area":270,"skill_cancel_time":0,"width":110,"hit_rate":1.6,"name":"亞馬遜射手","atk_script":"H102_normal_attack","height":180,"job":3,"bodytype":1.3,"hit_script":"hit_11"},"3019":{"path":"M019_output","img":"M019","skill":221,"actiontime":0.2,"speed":33,"skill_auto_script":"","next_skill":"S222_magic_M019_attack","skill_auto":0,"skill_script":"S221_magic_M019_attack","trail":0,"shadow":2,"hit_power":0,"id":3019,"atk_power":250,"hit_area":40,"skill_cancel_time":0.2,"width":140,"hit_rate":1.8,"name":"雪地食人妖","atk_script":"M019_normal_attack","height":240,"job":1,"bodytype":1.3,"hit_script":"hit_11"},"3005":{"path":"M005_output","img":"M005","skill":101,"actiontime":0.1,"speed":100,"skill_auto_script":"","next_skill":"S102_magic_M005_attack","skill_auto":0,"skill_script":"S101_magic_M005_attack","trail":0,"shadow":2,"hit_power":0,"id":3005,"atk_power":250,"hit_area":20,"skill_cancel_time":0,"width":70,"hit_rate":1.8,"name":"史萊姆女王","atk_script":"M005_normal_attack","height":130,"job":1,"bodytype":1.3,"hit_script":"hit_31"},"4092":{"path":"H092_output","img":"H092","skill":0,"actiontime":1,"speed":220,"skill_auto_script":"","next_skill":"","skill_auto":0,"skill_script":"","trail":0,"shadow":1,"hit_power":0,"id":4092,"atk_power":200,"hit_area":240,"skill_cancel_time":0,"width":60,"hit_rate":1.45,"name":"地獄巫女","atk_script":"H092_normal_attack","height":150,"job":2,"bodytype":1.3,"hit_script":"hit_11"},"4019":{"path":"H019_output","img":"H019","skill":421,"actiontime":0.2,"speed":150,"skill_auto_script":"H019_auto1_attack","next_skill":"S422_magic_H019_attack","skill_auto":611,"skill_script":"S421_magic_H019_attack","trail":1,"shadow":1,"hit_power":0,"id":4019,"atk_power":200,"hit_area":210,"skill_cancel_time":0.2,"width":100,"hit_rate":1.65,"name":"洛基","atk_script":"H019_normal_attack","height":200,"job":4,"bodytype":1.3,"hit_script":"hit_43"},"4075":{"path":"H075_output","img":"H075","skill":421,"actiontime":1,"speed":145,"skill_auto_script":"H075_auto1_attack","next_skill":"S422_magic_H075_attack","skill_auto":613,"skill_script":"S421_magic_H075_attack","trail":0,"shadow":1,"hit_power":0,"id":4075,"atk_power":200,"hit_area":215,"skill_cancel_time":0,"width":90,"hit_rate":1.65,"name":"赫拉","atk_script":"H075_normal_attack","height":200,"job":4,"bodytype":1.3,"hit_script":"hit_11"},"3075":{"path":"M075_output","img":"M075","skill":0,"actiontime":1,"speed":220,"skill_auto_script":"","next_skill":"","skill_auto":0,"skill_script":"","trail":0,"shadow":1,"hit_power":0,"id":3075,"atk_power":250,"hit_area":40,"skill_cancel_time":0,"width":80,"hit_rate":1.45,"name":"戰爭之樹","atk_script":"M075_normal_attack","height":200,"job":2,"bodytype":1.3,"hit_script":"hit_11"},"4101":{"path":"H101_output","img":"H101","skill":121,"actiontime":1,"speed":150,"skill_auto_script":"H101_normal_attack","next_skill":"S122_magic_H101_attack","skill_auto":610,"skill_script":"S121_magic_H101_attack","trail":0,"shadow":1,"hit_power":0,"id":4101,"atk_power":200,"hit_area":20,"skill_cancel_time":0,"width":110,"hit_rate":1.45,"name":"亞馬遜戰姬","atk_script":"H101_normal_attack","height":180,"job":2,"bodytype":1.3,"hit_script":"hit_11"},"4088":{"path":"H088_output","img":"H088","skill":421,"actiontime":1,"speed":130,"skill_auto_script":"H088_normal_attack","next_skill":"S422_magic_H088_attack","skill_auto":603,"skill_script":"S421_magic_H088_attack","trail":0,"shadow":1,"hit_power":0,"id":4088,"atk_power":200,"hit_area":200,"skill_cancel_time":0,"width":80,"hit_rate":1.65,"name":"吟遊詩人","atk_script":"H088_normal_attack","height":190,"job":4,"bodytype":1.3,"hit_script":"hit_11"},"4096":{"path":"H096_output","img":"H096","skill":0,"actiontime":1,"speed":160,"skill_auto_script":"","next_skill":"","skill_auto":0,"skill_script":"","trail":0,"shadow":1,"hit_power":0,"id":4096,"atk_power":200,"hit_area":40,"skill_cancel_time":0,"width":120,"hit_rate":1.45,"name":"人馬勇士","atk_script":"H096_normal_attack","height":230,"job":2,"bodytype":1.3,"hit_script":"hit_11"},"4095":{"path":"H095_output","img":"H095","skill":0,"actiontime":1,"speed":160,"skill_auto_script":"","next_skill":"","skill_auto":0,"skill_script":"","trail":0,"shadow":1,"hit_power":0,"id":4095,"atk_power":200,"hit_area":40,"skill_cancel_time":0,"width":120,"hit_rate":1.45,"name":"人馬無雙劍士","atk_script":"H095_normal_attack","height":230,"job":2,"bodytype":1.3,"hit_script":"hit_11"},"3006":{"path":"M006_output","img":"M006","skill":221,"actiontime":0.1,"speed":100,"skill_auto_script":"","next_skill":"S222_magic_M006_attack","skill_auto":0,"skill_script":"S221_magic_M006_attack","trail":0,"shadow":2,"hit_power":0,"id":3006,"atk_power":250,"hit_area":40,"skill_cancel_time":0.2,"width":70,"hit_rate":1.45,"name":"史萊姆國王","atk_script":"M006_normal_attack","height":130,"job":2,"bodytype":1.3,"hit_script":"hit_31"},"4006":{"path":"H006_output","img":"H006","skill":301,"actiontime":0.3,"speed":200,"skill_auto_script":"H006_auto1_attack","next_skill":"S302_magic_H006_attack","skill_auto":604,"skill_script":"S301_magic_H006_attack","trail":1,"shadow":1,"hit_power":0,"id":4006,"atk_power":200,"hit_area":280,"skill_cancel_time":0.2,"width":60,"hit_rate":1.6,"name":"丘比特","atk_script":"H006_normal_attack","height":170,"job":3,"bodytype":1.3,"hit_script":"hit_31"},"3028":{"path":"M028_output","img":"M028","skill":412,"actiontime":0.1,"speed":160,"skill_auto_script":"","next_skill":"S412_magic_M028_attack","skill_auto":0,"skill_script":"S412_magic_M028_attack","trail":1,"shadow":2,"hit_power":0,"id":3028,"atk_power":250,"hit_area":280,"skill_cancel_time":0.1,"width":70,"hit_rate":1.65,"name":"綠龍","atk_script":"M028_normal_attack","height":250,"job":4,"bodytype":0.9,"hit_script":"hit_42"},"3008":{"path":"M007_output","img":"M007","skill":221,"actiontime":0.1,"speed":80,"skill_auto_script":"","next_skill":"S221_magic_attack","skill_auto":0,"skill_script":"S221_magic_attack","trail":0,"shadow":3,"hit_power":0,"id":3008,"atk_power":250,"hit_area":40,"skill_cancel_time":0.2,"width":170,"hit_rate":1.45,"name":"獅鷲","atk_script":"M007_normal_attack","height":200,"job":2,"bodytype":1.3,"hit_script":"hit_51"},"3068":{"path":"M068_output","img":"M068","skill":0,"actiontime":1,"speed":220,"skill_auto_script":"","next_skill":"","skill_auto":0,"skill_script":"","trail":0,"shadow":1,"hit_power":0,"id":3068,"atk_power":250,"hit_area":40,"skill_cancel_time":0,"width":80,"hit_rate":1.45,"name":"牛頭人錘兵","atk_script":"M068_normal_attack","height":200,"job":2,"bodytype":1.3,"hit_script":"hit_11"},"4045":{"path":"H045_output","img":"H045","skill":0,"actiontime":0.2,"speed":220,"skill_auto_script":"","next_skill":"","skill_auto":0,"skill_script":"","trail":0,"shadow":1,"hit_power":0,"id":4045,"atk_power":200,"hit_area":40,"skill_cancel_time":0,"width":80,"hit_rate":1.45,"name":"希臘士兵","atk_script":"H045_normal_attack","height":210,"job":2,"bodytype":1.3,"hit_script":"hit_11"},"4072":{"path":"H072_output","img":"H072","skill":0,"actiontime":0.2,"speed":200,"skill_auto_script":"","next_skill":"","skill_auto":0,"skill_script":"","trail":0,"shadow":1,"hit_power":0,"id":4072,"atk_power":200,"hit_area":40,"skill_cancel_time":0,"width":60,"hit_rate":1.45,"name":"寒鐵氏族戰士","atk_script":"H072_normal_attack","height":150,"job":2,"bodytype":1.3,"hit_script":"hit_11"},"3072":{"path":"M072_output","img":"M072","skill":0,"actiontime":1,"speed":80,"skill_auto_script":"","next_skill":"","skill_auto":0,"skill_script":"","trail":0,"shadow":1,"hit_power":0,"id":3072,"atk_power":250,"hit_area":50,"skill_cancel_time":0,"width":120,"hit_rate":1.8,"name":"獨眼巨人戍衛","atk_script":"M072_normal_attack","height":240,"job":1,"bodytype":1.3,"hit_script":"hit_11"},"4089":{"path":"H089_output","img":"H089","skill":421,"actiontime":0.3,"speed":130,"skill_auto_script":"H089_normal_attack","next_skill":"S422_magic_H089_attack","skill_auto":603,"skill_script":"S421_magic_H089_attack","trail":0,"shadow":1,"hit_power":0,"id":4089,"atk_power":200,"hit_area":200,"skill_cancel_time":0.3,"width":70,"hit_rate":1.65,"name":"盲眼歌者","atk_script":"H089_normal_attack","height":180,"job":4,"bodytype":1.3,"hit_script":"hit_11"},"4028":{"path":"H028_output","img":"H028","skill":0,"actiontime":0.2,"speed":160,"skill_auto_script":"","next_skill":"","skill_auto":0,"skill_script":"","trail":1,"shadow":2,"hit_power":0,"id":4028,"atk_power":200,"hit_area":190,"skill_cancel_time":0,"width":90,"hit_rate":1.65,"name":"蛇妖制裁者","atk_script":"H028_normal_attack","height":210,"job":4,"bodytype":1.3,"hit_script":"hit_42"},"5017":{"path":"M017_output","img":"M017","skill":0,"actiontime":0.1,"speed":33,"skill_auto_script":"","next_skill":"","skill_auto":0,"skill_script":"","trail":0,"shadow":2,"hit_power":0,"id":5017,"atk_power":200,"hit_area":50,"skill_cancel_time":0.1,"width":140,"hit_rate":1.8,"name":"洞穴食人妖","atk_script":"M017_normal_attack","height":240,"job":1,"bodytype":1.3,"hit_script":"hit_11"},"3095":{"path":"M095_output","img":"M095","skill":0,"actiontime":1,"speed":160,"skill_auto_script":"","next_skill":"","skill_auto":0,"skill_script":"","trail":0,"shadow":1,"hit_power":0,"id":3095,"atk_power":250,"hit_area":280,"skill_cancel_time":0,"width":60,"hit_rate":1.65,"name":"紅色塞壬法師","atk_script":"M095_normal_attack","height":160,"job":4,"bodytype":1.3,"hit_script":"hit_11"},"3017":{"path":"M017_output","img":"M017","skill":221,"actiontime":0.1,"speed":33,"skill_auto_script":"","next_skill":"S222_magic_M017_attack","skill_auto":0,"skill_script":"S221_magic_M017_attack","trail":0,"shadow":2,"hit_power":0,"id":3017,"atk_power":250,"hit_area":40,"skill_cancel_time":0.1,"width":140,"hit_rate":1.8,"name":"洞穴食人妖","atk_script":"M017_normal_attack","height":240,"job":1,"bodytype":1.3,"hit_script":"hit_11"},"3055":{"path":"M055_output","img":"M055","skill":0,"actiontime":1,"speed":220,"skill_auto_script":"","next_skill":"","skill_auto":0,"skill_script":"","trail":0,"shadow":1,"hit_power":0,"id":3055,"atk_power":250,"hit_area":40,"skill_cancel_time":0,"width":80,"hit_rate":1.45,"name":"惡犬","atk_script":"M055_normal_attack","height":160,"job":2,"bodytype":1.3,"hit_script":"hit_11"},"3015":{"path":"M015_output","img":"M015","skill":322,"actiontime":1,"speed":220,"skill_auto_script":"","next_skill":"S322_magic_M015_attack","skill_auto":0,"skill_script":"S322_magic_M015_attack","trail":0,"shadow":3,"hit_power":0,"id":3015,"atk_power":250,"hit_area":40,"skill_cancel_time":0,"width":80,"hit_rate":1.45,"name":"斯庫拉","atk_script":"M015_normal_attack","height":200,"job":2,"bodytype":1.1,"hit_script":"hit_11"},"4015":{"path":"H015_output","img":"H015","skill":111,"actiontime":0.2,"speed":210,"skill_auto_script":"H015_normal_attack","next_skill":"S112_magic_H015_attack","skill_auto":617,"skill_script":"S111_magic_H015_attack","trail":0,"shadow":1,"hit_power":0,"id":4015,"atk_power":200,"hit_area":20,"skill_cancel_time":0.5,"width":90,"hit_rate":1.8,"name":"布倫希爾德","atk_script":"H015_normal_attack","height":190,"job":1,"bodytype":1.3,"hit_script":"hit_11"},"3097":{"path":"M097_output","img":"M097","skill":0,"actiontime":1,"speed":220,"skill_auto_script":"","next_skill":"","skill_auto":0,"skill_script":"","trail":0,"shadow":1,"hit_power":0,"id":3097,"atk_power":250,"hit_area":40,"skill_cancel_time":0,"width":60,"hit_rate":1.45,"name":"金色塞壬戰士","atk_script":"M097_normal_attack","height":160,"job":2,"bodytype":1.3,"hit_script":"hit_11"},"4090":{"path":"H090_output","img":"H090","skill":321,"actiontime":1,"speed":190,"skill_auto_script":"H090_auto1_attack","next_skill":"S322_magic_H090_attack","skill_auto":615,"skill_script":"S321_magic_H090_attack","trail":0,"shadow":1,"hit_power":0,"id":4090,"atk_power":200,"hit_area":280,"skill_cancel_time":0,"width":90,"hit_rate":1.6,"name":"貝瑟芬妮","atk_script":"H090_normal_attack","height":190,"job":3,"bodytype":1.3,"hit_script":"hit_31"},"4093":{"path":"H093_output","img":"H093","skill":412,"actiontime":1,"speed":220,"skill_auto_script":"","next_skill":"S412_magic_H093_attack","skill_auto":0,"skill_script":"S412_magic_H093_attack","trail":0,"shadow":1,"hit_power":0,"id":4093,"atk_power":200,"hit_area":280,"skill_cancel_time":0,"width":120,"hit_rate":1.65,"name":"喀戎","atk_script":"H093_normal_attack","height":230,"job":4,"bodytype":1.3,"hit_script":"hit_11"},"4097":{"path":"H097_output","img":"H097","skill":0,"actiontime":1,"speed":160,"skill_auto_script":"","next_skill":"","skill_auto":0,"skill_script":"","trail":0,"shadow":1,"hit_power":0,"id":4097,"atk_power":200,"hit_area":40,"skill_cancel_time":0,"width":120,"hit_rate":1.45,"name":"人馬無雙勇士","atk_script":"H097_normal_attack","height":230,"job":2,"bodytype":1.3,"hit_script":"hit_11"},"3054":{"path":"M054_output","img":"M054","skill":0,"actiontime":1,"speed":220,"skill_auto_script":"","next_skill":"","skill_auto":0,"skill_script":"","trail":0,"shadow":1,"hit_power":0,"id":3054,"atk_power":250,"hit_area":40,"skill_cancel_time":0,"width":80,"hit_rate":1.45,"name":"加姆","atk_script":"M054_normal_attack","height":160,"job":2,"bodytype":1.3,"hit_script":"hit_11"},"4054":{"path":"H054_output","img":"H054","skill":201,"actiontime":0.3,"speed":170,"skill_auto_script":"H054_normal_attack","next_skill":"S202_magic_H054_attack","skill_auto":616,"skill_script":"S201_magic_H054_attack","trail":0,"shadow":1,"hit_power":0,"id":4054,"atk_power":200,"hit_area":40,"skill_cancel_time":0.4,"width":100,"hit_rate":1.45,"name":"伊阿宋","atk_script":"H054_normal_attack","height":210,"job":2,"bodytype":1.3,"hit_script":"hit_11"},"4005":{"path":"H005_output","img":"H005","skill":421,"actiontime":0.3,"speed":120,"skill_auto_script":"H005_auto1_attack","next_skill":"S422_magic_H005_attack","skill_auto":614,"skill_script":"S421_magic_H005_attack","trail":1,"shadow":1,"hit_power":0,"id":4005,"atk_power":200,"hit_area":220,"skill_cancel_time":0.1,"width":80,"hit_rate":1.65,"name":"維納斯","atk_script":"H005_normal_attack","height":220,"job":4,"bodytype":1.3,"hit_script":"hit_11"},"4085":{"path":"H085_output","img":"H085","skill":401,"actiontime":1,"speed":110,"skill_auto_script":"H085_normal_attack","next_skill":"S402_magic_H085_attack","skill_auto":601,"skill_script":"S401_magic_H085_attack","trail":0,"shadow":1,"hit_power":0,"id":4085,"atk_power":200,"hit_area":190,"skill_cancel_time":0,"width":75,"hit_rate":1.65,"name":"綠繆斯女神","atk_script":"H085_normal_attack","height":190,"job":4,"bodytype":1.3,"hit_script":"hit_11"},"3076":{"path":"M076_output","img":"M076","skill":0,"actiontime":1,"speed":220,"skill_auto_script":"","next_skill":"","skill_auto":0,"skill_script":"","trail":0,"shadow":1,"hit_power":0,"id":3076,"atk_power":250,"hit_area":40,"skill_cancel_time":0,"width":80,"hit_rate":1.45,"name":"智慧古樹","atk_script":"M076_normal_attack","height":200,"job":2,"bodytype":1.3,"hit_script":"hit_11"},"4076":{"path":"H076_output","img":"H076","skill":211,"actiontime":0.2,"speed":180,"skill_auto_script":"H076_auto1_attack","next_skill":"S212_magic_H076_attack","skill_auto":614,"skill_script":"S211_magic_H076_attack","trail":0,"shadow":1,"hit_power":0,"id":4076,"atk_power":200,"hit_area":50,"skill_cancel_time":0.2,"width":100,"hit_rate":1.45,"name":"波塞冬","atk_script":"H076_normal_attack","height":215,"job":2,"bodytype":1.3,"hit_script":"hit_11"},"4084":{"path":"H084_output","img":"H084","skill":301,"actiontime":1,"speed":170,"skill_auto_script":"H084_normal_attack","next_skill":"S302_magic_H084_attack","skill_auto":617,"skill_script":"S301_magic_H084_attack","trail":0,"shadow":1,"hit_power":0,"id":4084,"atk_power":200,"hit_area":270,"skill_cancel_time":0,"width":75,"hit_rate":1.6,"name":"藍繆斯女神","atk_script":"H084_normal_attack","height":190,"job":3,"bodytype":1.3,"hit_script":"hit_11"},"4083":{"path":"H083_output","img":"H083","skill":301,"actiontime":1,"speed":160,"skill_auto_script":"H083_normal_attack","next_skill":"S302_magic_H083_attack","skill_auto":617,"skill_script":"S301_magic_H083_attack","trail":0,"shadow":1,"hit_power":0,"id":4083,"atk_power":200,"hit_area":260,"skill_cancel_time":0,"width":75,"hit_rate":1.6,"name":"金繆斯女神","atk_script":"H083_normal_attack","height":190,"job":3,"bodytype":1.3,"hit_script":"hit_11"},"4044":{"path":"H044_output","img":"H044","skill":101,"actiontime":0.4,"speed":180,"skill_auto_script":"H044_normal_attack","next_skill":"S102_magic_H044_attack","skill_auto":603,"skill_script":"S101_magic_H044_attack","trail":0,"shadow":1,"hit_power":0,"id":4044,"atk_power":200,"hit_area":20,"skill_cancel_time":0.2,"width":90,"hit_rate":1.8,"name":"赫克托爾","atk_script":"H044_normal_attack","height":220,"job":1,"bodytype":1.3,"hit_script":"hit_11"},"3044":{"path":"M044_output","img":"M044","skill":0,"actiontime":0.2,"speed":220,"skill_auto_script":"","next_skill":"","skill_auto":0,"skill_script":"","trail":0,"shadow":1,"hit_power":0,"id":3044,"atk_power":250,"hit_area":40,"skill_cancel_time":0,"width":80,"hit_rate":1.45,"name":"大石像鬼","atk_script":"M044_normal_attack","height":200,"job":2,"bodytype":1.3,"hit_script":"hit_11"},"4049":{"path":"H049_output","img":"H049","skill":121,"actiontime":0.4,"speed":200,"skill_auto_script":"H049_auto1_attack","next_skill":"S122_magic_H049_attack","skill_auto":607,"skill_script":"S121_magic_H049_attack","trail":0,"shadow":2,"hit_power":0,"id":4049,"atk_power":200,"hit_area":20,"skill_cancel_time":0.3,"width":90,"hit_rate":1.8,"name":"列奧尼達","atk_script":"H049_normal_attack","height":220,"job":1,"bodytype":1.3,"hit_script":"hit_11"},"3084":{"path":"M084_output","img":"M084","skill":0,"actiontime":1,"speed":220,"skill_auto_script":"","next_skill":"","skill_auto":0,"skill_script":"","trail":0,"shadow":1,"hit_power":0,"id":3084,"atk_power":250,"hit_area":40,"skill_cancel_time":0,"width":60,"hit_rate":1.45,"name":"小冰霜巨人","atk_script":"M084_normal_attack","height":160,"job":2,"bodytype":1.3,"hit_script":"hit_11"},"4066":{"path":"H066_output","img":"H066","skill":221,"actiontime":0.1,"speed":320,"skill_auto_script":"","next_skill":"S222_magic_H066_attack","skill_auto":0,"skill_script":"S221_magic_H066_attack","trail":0,"shadow":3,"hit_power":0,"id":4066,"atk_power":200,"hit_area":20,"skill_cancel_time":0.1,"width":140,"hit_rate":1.45,"name":"聖地守護者","atk_script":"H066_normal_attack","height":210,"job":2,"bodytype":1.3,"hit_script":"hit_11"},"3066":{"path":"M066_output","img":"M066","skill":0,"actiontime":1,"speed":220,"skill_auto_script":"","next_skill":"","skill_auto":0,"skill_script":"","trail":0,"shadow":1,"hit_power":0,"id":3066,"atk_power":250,"hit_area":40,"skill_cancel_time":0,"width":80,"hit_rate":1.45,"name":"牛頭人斧兵","atk_script":"M066_normal_attack","height":200,"job":2,"bodytype":1.3,"hit_script":"hit_11"},"3079":{"path":"M079_output","img":"M079","skill":0,"actiontime":1,"speed":220,"skill_auto_script":"","next_skill":"","skill_auto":0,"skill_script":"","trail":0,"shadow":1,"hit_power":0,"id":3079,"atk_power":250,"hit_area":40,"skill_cancel_time":0,"width":80,"hit_rate":1.45,"name":"樹人保護者","atk_script":"M079_normal_attack","height":200,"job":2,"bodytype":1.3,"hit_script":"hit_11"},"4074":{"path":"H074_output","img":"H074","skill":0,"actiontime":0.2,"speed":150,"skill_auto_script":"","next_skill":"","skill_auto":0,"skill_script":"","trail":0,"shadow":1,"hit_power":0,"id":4074,"atk_power":200,"hit_area":250,"skill_cancel_time":0,"width":60,"hit_rate":1.6,"name":"寒鐵氏族投手","atk_script":"H074_normal_attack","height":150,"job":3,"bodytype":1.3,"hit_script":"hit_11"},"3096":{"path":"M096_output","img":"M096","skill":0,"actiontime":1,"speed":220,"skill_auto_script":"","next_skill":"","skill_auto":0,"skill_script":"","trail":0,"shadow":1,"hit_power":0,"id":3096,"atk_power":250,"hit_area":40,"skill_cancel_time":0,"width":60,"hit_rate":1.45,"name":"綠色塞壬戰士","atk_script":"M096_normal_attack","height":160,"job":2,"bodytype":1.3,"hit_script":"hit_11"},"3049":{"path":"M049_output","img":"M049","skill":121,"actiontime":0.2,"speed":220,"skill_auto_script":"","next_skill":"S122_magic_M049_attack","skill_auto":0,"skill_script":"S121_magic_M049_attack","trail":0,"shadow":1,"hit_power":0,"id":3049,"atk_power":250,"hit_area":40,"skill_cancel_time":0,"width":60,"hit_rate":1.45,"name":"撕咬蝙蝠王","atk_script":"M049_normal_attack","height":200,"job":2,"bodytype":1.3,"hit_script":"hit_11"},"4080":{"path":"H080_output","img":"H080","skill":201,"actiontime":1,"speed":180,"skill_auto_script":"H080_auto1_attack","next_skill":"S202_magic_H080_attack","skill_auto":606,"skill_script":"S201_magic_H080_attack","trail":0,"shadow":1,"hit_power":0,"id":4080,"atk_power":200,"hit_area":50,"skill_cancel_time":0,"width":130,"hit_rate":1.45,"name":"塔那托斯","atk_script":"H080_normal_attack","height":250,"job":2,"bodytype":1.3,"hit_script":"hit_11"},"4039":{"path":"H039_output","img":"H039","skill":301,"actiontime":0.5,"speed":180,"skill_auto_script":"H039_normal_attack","next_skill":"S302_magic_H039_attack","skill_auto":605,"skill_script":"S301_magic_H039_attack","trail":1,"shadow":1,"hit_power":0,"id":4039,"atk_power":200,"hit_area":260,"skill_cancel_time":0.6,"width":120,"hit_rate":1.6,"name":"帕里斯","atk_script":"H039_normal_attack","height":200,"job":3,"bodytype":1.3,"hit_script":"hit_31"},"3039":{"path":"M039_output","img":"M039","skill":0,"actiontime":0.1,"speed":220,"skill_auto_script":"","next_skill":"","skill_auto":0,"skill_script":"","trail":0,"shadow":1,"hit_power":0,"id":3039,"atk_power":250,"hit_area":40,"skill_cancel_time":0,"width":60,"hit_rate":1.45,"name":"彩色鷹身女妖","atk_script":"M039_normal_attack","height":200,"job":2,"bodytype":1.3,"hit_script":"hit_11"},"4079":{"path":"H079_output","img":"H079","skill":121,"actiontime":1,"speed":210,"skill_auto_script":"H079_auto1_attack","next_skill":"S122_magic_H079_attack","skill_auto":616,"skill_script":"S121_magic_H079_attack","trail":0,"shadow":1,"hit_power":0,"id":4079,"atk_power":200,"hit_area":40,"skill_cancel_time":0,"width":110,"hit_rate":1.8,"name":"赫斐斯托斯","atk_script":"H079_normal_attack","height":200,"job":1,"bodytype":1.3,"hit_script":"hit_11"},"4064":{"path":"H064_output","img":"H064","skill":411,"actiontime":0.3,"speed":110,"skill_auto_script":"H064_normal_attack","next_skill":"S412_magic_H064_attack","skill_auto":602,"skill_script":"S411_magic_H064_attack","trail":1,"shadow":1,"hit_power":0,"id":4064,"atk_power":200,"hit_area":220,"skill_cancel_time":0.4,"width":90,"hit_rate":1.65,"name":"凱蘭崔爾","atk_script":"H064_normal_attack","height":200,"job":4,"bodytype":1.3,"hit_script":"hit_42"},"3064":{"path":"M064_output","img":"M064","skill":221,"actiontime":0.1,"speed":110,"skill_auto_script":"","next_skill":"S222_magic_attack","skill_auto":0,"skill_script":"S221_magic_attack","trail":0,"shadow":2,"hit_power":0,"id":3064,"atk_power":250,"hit_area":40,"skill_cancel_time":0.4,"width":100,"hit_rate":1.45,"name":"彌諾陶洛斯","atk_script":"M064_normal_attack","height":230,"job":2,"bodytype":1.3,"hit_script":"hit_11"},"4002":{"path":"H002_output","img":"H002","skill":101,"actiontime":0.2,"speed":180,"skill_auto_script":"H002_auto1_attack","next_skill":"S102_magic_H002_attack","skill_auto":612,"skill_script":"S101_magic_H002_attack","trail":0,"shadow":1,"hit_power":0,"id":4002,"atk_power":200,"hit_area":20,"skill_cancel_time":0.1,"width":90,"hit_rate":1.8,"name":"雅典娜","atk_script":"H002_normal_attack","height":205,"job":1,"bodytype":1.3,"hit_script":"hit_11"},"4077":{"path":"H077_output","img":"H077","skill":121,"actiontime":0.2,"speed":350,"skill_auto_script":"H077_auto1_attack","next_skill":"S122_magic_H077_attack","skill_auto":616,"skill_script":"S121_magic_H077_attack","trail":0,"shadow":1,"hit_power":0,"id":4077,"atk_power":200,"hit_area":20,"skill_cancel_time":0.2,"width":90,"hit_rate":1.8,"name":"哈迪斯","atk_script":"H077_normal_attack","height":210,"job":1,"bodytype":1.3,"hit_script":"hit_11"},"4073":{"path":"H073_output","img":"H073","skill":0,"actiontime":0.2,"speed":150,"skill_auto_script":"","next_skill":"","skill_auto":0,"skill_script":"","trail":0,"shadow":1,"hit_power":0,"id":4073,"atk_power":200,"hit_area":250,"skill_cancel_time":0,"width":60,"hit_rate":1.6,"name":"深火氏族投手","atk_script":"H073_normal_attack","height":150,"job":3,"bodytype":1.3,"hit_script":"hit_11"},"4070":{"path":"H070_output","img":"H070","skill":411,"actiontime":0.3,"speed":110,"skill_auto_script":"H070_normal_attack","next_skill":"S412_magic_H070_attack","skill_auto":603,"skill_script":"S411_magic_H070_attack","trail":1,"shadow":1,"hit_power":0,"id":4070,"atk_power":200,"hit_area":190,"skill_cancel_time":0.2,"width":80,"hit_rate":1.65,"name":"法夫納","atk_script":"H070_normal_attack","height":170,"job":4,"bodytype":1.3,"hit_script":"hit_42"},"4008":{"path":"H008_output","img":"H008","skill":411,"actiontime":0.5,"speed":140,"skill_auto_script":"H008_auto1_attack","next_skill":"S412_magic_H008_attack","skill_auto":610,"skill_script":"S411_magic_H008_attack","trail":0,"shadow":1,"hit_power":0,"id":4008,"atk_power":200,"hit_area":210,"skill_cancel_time":0.5,"width":80,"hit_rate":1.65,"name":"普羅米修士","atk_script":"H008_normal_attack","height":230,"job":4,"bodytype":1.3,"hit_script":"hit_42"},"3101":{"path":"M100_output","img":"M100","skill":402,"actiontime":0.1,"speed":190,"skill_auto_script":"","next_skill":"S402_magic_M100_attack","skill_auto":0,"skill_script":"S402_magic_M100_attack","trail":0,"shadow":3,"hit_power":0,"id":3101,"atk_power":250,"hit_area":80,"skill_cancel_time":0.1,"width":350,"hit_rate":1.45,"name":"煉獄邪龍","atk_script":"M100_normal_attack","height":250,"job":2,"bodytype":1.1,"hit_script":""},"3065":{"path":"M065_output","img":"M065","skill":0,"actiontime":1,"speed":220,"skill_auto_script":"","next_skill":"","skill_auto":0,"skill_script":"","trail":0,"shadow":1,"hit_power":0,"id":3065,"atk_power":250,"hit_area":40,"skill_cancel_time":0,"width":80,"hit_rate":1.45,"name":"火牛","atk_script":"M065_normal_attack","height":200,"job":2,"bodytype":1.3,"hit_script":"hit_11"},"4065":{"path":"H065_output","img":"H065","skill":301,"actiontime":0.2,"speed":320,"skill_auto_script":"","next_skill":"S302_magic_H065_attack","skill_auto":0,"skill_script":"S301_magic_H065_attack","trail":1,"shadow":3,"hit_power":0,"id":4065,"atk_power":200,"hit_area":270,"skill_cancel_time":0.2,"width":140,"hit_rate":1.6,"name":"精靈禁衛軍","atk_script":"H065_normal_attack","height":210,"job":3,"bodytype":1.3,"hit_script":"hit_11"},"4069":{"path":"H069_output","img":"H069","skill":101,"actiontime":0.2,"speed":100,"skill_auto_script":"H069_normal_attack","next_skill":"S102_magic_H069_attack","skill_auto":605,"skill_script":"S101_magic_H069_attack","trail":0,"shadow":1,"hit_power":0,"id":4069,"atk_power":200,"hit_area":20,"skill_cancel_time":0,"width":90,"hit_rate":1.8,"name":"索林·橡木盾","atk_script":"H069_normal_attack","height":170,"job":1,"bodytype":1.3,"hit_script":"hit_11"},"4068":{"path":"H068_output","img":"H068","skill":221,"actiontime":0.1,"speed":320,"skill_auto_script":"","next_skill":"S222_magic_H068_attack","skill_auto":0,"skill_script":"S221_magic_H068_attack","trail":0,"shadow":3,"hit_power":0,"id":4068,"atk_power":200,"hit_area":20,"skill_cancel_time":0.1,"width":140,"hit_rate":1.45,"name":"黑暗聖地守護者","atk_script":"H068_normal_attack","height":210,"job":2,"bodytype":1.3,"hit_script":"hit_11"},"4107":{"path":"H107_output","img":"H107","skill":201,"actiontime":0.3,"speed":200,"skill_auto_script":"H107_auto1_attack","next_skill":"S202_magic_H107_attack","skill_auto":604,"skill_script":"S201_magic_H107_attack","trail":0,"shadow":1,"hit_power":0,"id":4107,"atk_power":200,"hit_area":40,"skill_cancel_time":0.3,"width":80,"hit_rate":1.45,"name":"珀修斯","atk_script":"H107_normal_attack","height":180,"job":2,"bodytype":1.3,"hit_script":"hit_11"},"4061":{"path":"H061_output","img":"H061","skill":301,"actiontime":0.5,"speed":170,"skill_auto_script":"H061_normal_attack","next_skill":"S302_magic_H061_attack","skill_auto":611,"skill_script":"S301_magic_H061_attack","trail":1,"shadow":1,"hit_power":0,"id":4061,"atk_power":200,"hit_area":270,"skill_cancel_time":0.5,"width":100,"hit_rate":1.6,"name":"希爾瓦娜斯","atk_script":"H061_normal_attack","height":200,"job":3,"bodytype":1.3,"hit_script":"hit_31"},"4059":{"path":"H059_output","img":"H059","skill":0,"actiontime":0.1,"speed":190,"skill_auto_script":"","next_skill":"","skill_auto":0,"skill_script":"","trail":0,"shadow":1,"hit_power":0,"id":4059,"atk_power":200,"hit_area":40,"skill_cancel_time":0,"width":60,"hit_rate":1.45,"name":"精靈戰士","atk_script":"H059_normal_attack","height":190,"job":2,"bodytype":1.3,"hit_script":"hit_11"},"4058":{"path":"H058_output","img":"H058","skill":201,"actiontime":0.2,"speed":220,"skill_auto_script":"H058_normal_attack","next_skill":"S202_magic_H058_attack","skill_auto":613,"skill_script":"S201_magic_H058_attack","trail":0,"shadow":1,"hit_power":0,"id":4058,"atk_power":200,"hit_area":40,"skill_cancel_time":0.3,"width":100,"hit_rate":1.45,"name":"泰蘭德","atk_script":"H058_normal_attack","height":200,"job":2,"bodytype":1.3,"hit_script":"hit_11"},"4032":{"path":"H032_output","img":"H032","skill":0,"actiontime":0.2,"speed":120,"skill_auto_script":"","next_skill":"","skill_auto":0,"skill_script":"","trail":0,"shadow":2,"hit_power":0,"id":4032,"atk_power":200,"hit_area":40,"skill_cancel_time":0,"width":120,"hit_rate":1.8,"name":"波斯騎兵","atk_script":"H032_normal_attack","height":230,"job":1,"bodytype":1.3,"hit_script":"hit_11"},"3074":{"path":"M074_output","img":"M074","skill":0,"actiontime":1,"speed":220,"skill_auto_script":"","next_skill":"","skill_auto":0,"skill_script":"","trail":0,"shadow":1,"hit_power":0,"id":3074,"atk_power":250,"hit_area":40,"skill_cancel_time":0,"width":80,"hit_rate":1.45,"name":"戰爭古樹","atk_script":"M074_normal_attack","height":200,"job":2,"bodytype":1.3,"hit_script":"hit_11"},"4055":{"path":"H055_output","img":"H055","skill":221,"actiontime":0.3,"speed":200,"skill_auto_script":"H055_normal_attack","next_skill":"S222_magic_H055_attack","skill_auto":617,"skill_script":"S221_magic_H055_attack","trail":0,"shadow":1,"hit_power":0,"id":4055,"atk_power":200,"hit_area":40,"skill_cancel_time":0.2,"width":100,"hit_rate":1.45,"name":"阿喀琉斯","atk_script":"H055_normal_attack","height":210,"job":2,"bodytype":1.3,"hit_script":"hit_11"},"4053":{"path":"H048_output","img":"H053","skill":0,"actiontime":0.1,"speed":180,"skill_auto_script":"","next_skill":"","skill_auto":0,"skill_script":"","trail":0,"shadow":1,"hit_power":0,"id":4053,"atk_power":200,"hit_area":20,"skill_cancel_time":0,"width":80,"hit_rate":1.8,"name":"特洛伊方陣兵","atk_script":"H053_normal_attack","height":210,"job":1,"bodytype":1.3,"hit_script":"hit_11"},"3010":{"path":"M010_output","img":"M010","skill":0,"actiontime":0.1,"speed":220,"skill_auto_script":"","next_skill":"","skill_auto":0,"skill_script":"","trail":0,"shadow":1,"hit_power":0,"id":3010,"atk_power":250,"hit_area":40,"skill_cancel_time":0,"width":60,"hit_rate":1.45,"name":"大雕","atk_script":"M010_normal_attack","height":200,"job":1,"bodytype":1.3,"hit_script":"hit_51"},"4051":{"path":"H046_output","img":"H051","skill":0,"actiontime":0.2,"speed":220,"skill_auto_script":"","next_skill":"","skill_auto":0,"skill_script":"","trail":0,"shadow":1,"hit_power":0,"id":4051,"atk_power":200,"hit_area":20,"skill_cancel_time":0,"width":100,"hit_rate":1.8,"name":"希臘方陣兵","atk_script":"H051_normal_attack","height":220,"job":1,"bodytype":1.3,"hit_script":"hit_11"},"4048":{"path":"H048_output","img":"H048","skill":0,"actiontime":0.2,"speed":200,"skill_auto_script":"","next_skill":"","skill_auto":0,"skill_script":"","trail":0,"shadow":1,"hit_power":0,"id":4048,"atk_power":200,"hit_area":40,"skill_cancel_time":0,"width":100,"hit_rate":1.45,"name":"特洛伊精兵","atk_script":"H048_normal_attack","height":210,"job":2,"bodytype":1.3,"hit_script":"hit_11"},"4010":{"path":"H010_output","img":"H010","skill":0,"actiontime":0.1,"speed":100,"skill_auto_script":"","next_skill":"","skill_auto":0,"skill_script":"","trail":0,"shadow":2,"hit_power":0,"id":4010,"atk_power":200,"hit_area":40,"skill_cancel_time":0,"width":120,"hit_rate":1.45,"name":"角鬥士","atk_script":"H010_normal_attack","height":180,"job":2,"bodytype":1.3,"hit_script":"hit_11"},"4027":{"path":"H027_output","img":"H027","skill":0,"actiontime":0.1,"speed":160,"skill_auto_script":"","next_skill":"","skill_auto":0,"skill_script":"","trail":0,"shadow":2,"hit_power":0,"id":4027,"atk_power":200,"hit_area":40,"skill_cancel_time":0,"width":100,"hit_rate":1.45,"name":"蛇妖破法者","atk_script":"H027_normal_attack","height":210,"job":2,"bodytype":1.3,"hit_script":"hit_11"},"4047":{"path":"H047_output","img":"H047","skill":0,"actiontime":0.2,"speed":200,"skill_auto_script":"","next_skill":"","skill_auto":0,"skill_script":"","trail":0,"shadow":1,"hit_power":0,"id":4047,"atk_power":200,"hit_area":40,"skill_cancel_time":0,"width":100,"hit_rate":1.45,"name":"特洛伊士兵","atk_script":"H047_normal_attack","height":210,"job":2,"bodytype":1.3,"hit_script":"hit_11"},"4001":{"path":"H001_output","img":"H001","skill":401,"actiontime":0.4,"speed":100,"skill_auto_script":"H001_normal_attack","next_skill":"S402_magic_H001_attack","skill_auto":617,"skill_script":"S401_magic_H001_attack","trail":0,"shadow":1,"hit_power":0,"id":4001,"atk_power":200,"hit_area":200,"skill_cancel_time":0.2,"width":60,"hit_rate":1.65,"name":"奧德修斯","atk_script":"H001_normal_attack","height":200,"job":4,"bodytype":1.4,"hit_script":"hit_41"},"3027":{"path":"M027_output","img":"M027","skill":412,"actiontime":0.1,"speed":160,"skill_auto_script":"","next_skill":"S412_magic_M027_attack","skill_auto":0,"skill_script":"S412_magic_M027_attack","trail":1,"shadow":2,"hit_power":0,"id":3027,"atk_power":250,"hit_area":280,"skill_cancel_time":0.1,"width":70,"hit_rate":1.65,"name":"紅龍","atk_script":"M027_normal_attack","height":250,"job":4,"bodytype":0.9,"hit_script":"hit_42"},"4067":{"path":"H067_output","img":"H067","skill":301,"actiontime":0.2,"speed":320,"skill_auto_script":"","next_skill":"S302_magic_H067_attack","skill_auto":0,"skill_script":"S301_magic_H067_attack","trail":1,"shadow":3,"hit_power":0,"id":4067,"atk_power":200,"hit_area":270,"skill_cancel_time":0.2,"width":140,"hit_rate":1.6,"name":"黑暗精靈禁衛軍","atk_script":"H067_normal_attack","height":210,"job":3,"bodytype":1.3,"hit_script":"hit_11"},"3067":{"path":"M067_output","img":"M067","skill":0,"actiontime":1,"speed":220,"skill_auto_script":"","next_skill":"","skill_auto":0,"skill_script":"","trail":0,"shadow":1,"hit_power":0,"id":3067,"atk_power":250,"hit_area":40,"skill_cancel_time":0,"width":80,"hit_rate":1.45,"name":"高級牛頭人斧兵","atk_script":"M067_normal_attack","height":200,"job":2,"bodytype":1.3,"hit_script":"hit_11"},"4020":{"path":"H020_output","img":"H020","skill":101,"actiontime":0.2,"speed":150,"skill_auto_script":"H020_normal_attack","next_skill":"S102_magic_H020_attack","skill_auto":612,"skill_script":"S101_magic_H020_attack","trail":0,"shadow":1,"hit_power":0,"id":4020,"atk_power":200,"hit_area":20,"skill_cancel_time":0.2,"width":80,"hit_rate":1.8,"name":"海姆達爾","atk_script":"H020_normal_attack","height":230,"job":1,"bodytype":1.3,"hit_script":"hit_11"},"4034":{"path":"H032_output","img":"H034","skill":0,"actiontime":0.2,"speed":120,"skill_auto_script":"","next_skill":"","skill_auto":0,"skill_script":"","trail":1,"shadow":2,"hit_power":0,"id":4034,"atk_power":200,"hit_area":250,"skill_cancel_time":0,"width":120,"hit_rate":1.6,"name":"波斯騎射手","atk_script":"H034_normal_attack","height":230,"job":3,"bodytype":1.3,"hit_script":"hit_11"},"3009":{"path":"M009_output","img":"M009","skill":0,"actiontime":0.1,"speed":220,"skill_auto_script":"","next_skill":"","skill_auto":0,"skill_script":"","trail":0,"shadow":1,"hit_power":0,"id":3009,"atk_power":250,"hit_area":40,"skill_cancel_time":0,"width":60,"hit_rate":1.45,"name":"巨鷹","atk_script":"M009_normal_attack","height":200,"job":2,"bodytype":1.3,"hit_script":"hit_51"},"3014":{"path":"M014_output","img":"M014","skill":402,"actiontime":0.1,"speed":190,"skill_auto_script":"","next_skill":"S402_magic_M014_attack","skill_auto":0,"skill_script":"S402_magic_M014_attack","trail":0,"shadow":3,"hit_power":0,"id":3014,"atk_power":250,"hit_area":80,"skill_cancel_time":0.1,"width":450,"hit_rate":1.65,"name":"許德拉","atk_script":"M014_normal_attack","height":320,"job":4,"bodytype":1.1,"hit_script":""},"3045":{"path":"M045_output","img":"M045","skill":0,"actiontime":0.2,"speed":220,"skill_auto_script":"","next_skill":"","skill_auto":0,"skill_script":"","trail":0,"shadow":1,"hit_power":0,"id":3045,"atk_power":250,"hit_area":40,"skill_cancel_time":0,"width":40,"hit_rate":1.45,"name":"青色撕咬蝙蝠","atk_script":"M045_normal_attack","height":200,"job":2,"bodytype":1.3,"hit_script":"hit_11"},"4009":{"path":"H009_output","img":"H009","skill":211,"actiontime":0.2,"speed":210,"skill_auto_script":"H009_auto1_attack","next_skill":"S212_magic_H009_attack","skill_auto":615,"skill_script":"S211_magic_H009_attack","trail":0,"shadow":1,"hit_power":0,"id":4009,"atk_power":200,"hit_area":40,"skill_cancel_time":0.1,"width":100,"hit_rate":1.45,"name":"海格力斯","atk_script":"H009_normal_attack","height":160,"job":2,"bodytype":1.3,"hit_script":"hit_11"},"3057":{"path":"M057_output","img":"M057","skill":0,"actiontime":1,"speed":220,"skill_auto_script":"","next_skill":"","skill_auto":0,"skill_script":"","trail":0,"shadow":1,"hit_power":0,"id":3057,"atk_power":250,"hit_area":40,"skill_cancel_time":0,"width":80,"hit_rate":1.45,"name":"座狼","atk_script":"M057_normal_attack","height":160,"job":2,"bodytype":1.3,"hit_script":"hit_11"},"4057":{"path":"H057_output","img":"H057","skill":0,"actiontime":0.2,"speed":160,"skill_auto_script":"","next_skill":"","skill_auto":0,"skill_script":"","trail":1,"shadow":1,"hit_power":0,"id":4057,"atk_power":200,"hit_area":260,"skill_cancel_time":0.2,"width":80,"hit_rate":1.6,"name":"黑暗精靈射手","atk_script":"H057_normal_attack","height":190,"job":3,"bodytype":1.3,"hit_script":"hit_31"},"3086":{"path":"M086_output","img":"M086","skill":0,"actiontime":1,"speed":220,"skill_auto_script":"","next_skill":"","skill_auto":0,"skill_script":"","trail":0,"shadow":1,"hit_power":0,"id":3086,"atk_power":250,"hit_area":40,"skill_cancel_time":0,"width":60,"hit_rate":1.45,"name":"小石巨人","atk_script":"M086_normal_attack","height":160,"job":2,"bodytype":1.3,"hit_script":"hit_11"},"4108":{"path":"H108_output","img":"H108","skill":411,"actiontime":0.3,"speed":150,"skill_auto_script":"H108_normal_attack","next_skill":"S412_magic_H108_attack","skill_auto":602,"skill_script":"S411_magic_H108_attack","trail":0,"shadow":1,"hit_power":0,"id":4108,"atk_power":200,"hit_area":210,"skill_cancel_time":0.3,"width":60,"hit_rate":1.65,"name":"紗織","atk_script":"H108_normal_attack","height":160,"job":4,"bodytype":1.3,"hit_script":"hit_42"},"3033":{"path":"M033_output","img":"M033","skill":0,"actiontime":0.2,"speed":220,"skill_auto_script":"","next_skill":"","skill_auto":0,"skill_script":"","trail":0,"shadow":1,"hit_power":0,"id":3033,"atk_power":250,"hit_area":40,"skill_cancel_time":0,"width":100,"hit_rate":1.45,"name":"小綠龍","atk_script":"M033_normal_attack","height":190,"job":2,"bodytype":1.3,"hit_script":"hit_42"},"4033":{"path":"H033_output","img":"H033","skill":0,"actiontime":0.2,"speed":120,"skill_auto_script":"","next_skill":"","skill_auto":0,"skill_script":"","trail":0,"shadow":2,"hit_power":0,"id":4033,"atk_power":200,"hit_area":40,"skill_cancel_time":0,"width":120,"hit_rate":1.8,"name":"波斯重裝騎兵","atk_script":"H033_normal_attack","height":230,"job":1,"bodytype":1.3,"hit_script":"hit_11"},"4025":{"path":"H025_output","img":"H025","skill":211,"actiontime":0.2,"speed":160,"skill_auto_script":"","next_skill":"S212_magic_H025_attack","skill_auto":0,"skill_script":"S211_magic_H025_attack","trail":0,"shadow":2,"hit_power":0,"id":4025,"atk_power":200,"hit_area":40,"skill_cancel_time":0.2,"width":100,"hit_rate":1.45,"name":"厄喀德那","atk_script":"H025_normal_attack","height":210,"job":2,"bodytype":1.3,"hit_script":"hit_11"},"3061":{"path":"M061_output","img":"M061","skill":202,"actiontime":2,"speed":220,"skill_auto_script":"","next_skill":"S202_magic_M061_attack","skill_auto":0,"skill_script":"S221_magic_M059_attack","trail":0,"shadow":1,"hit_power":0,"id":3061,"atk_power":250,"hit_area":40,"skill_cancel_time":0,"width":80,"hit_rate":1.45,"name":"金色塔羅斯","atk_script":"M061_normal_attack","height":160,"job":2,"bodytype":1.3,"hit_script":"hit_11"},"3094":{"path":"M094_output","img":"M094","skill":0,"actiontime":1,"speed":160,"skill_auto_script":"","next_skill":"","skill_auto":0,"skill_script":"","trail":0,"shadow":1,"hit_power":0,"id":3094,"atk_power":250,"hit_area":280,"skill_cancel_time":0,"width":60,"hit_rate":1.65,"name":"藍色塞壬法師","atk_script":"M094_normal_attack","height":160,"job":4,"bodytype":1.3,"hit_script":"hit_11"},"4007":{"path":"H007_output","img":"H007","skill":221,"actiontime":0.1,"speed":180,"skill_auto_script":"H007_auto1_attack","next_skill":"S222_magic_H007_attack","skill_auto":612,"skill_script":"S221_magic_H007_attack","trail":0,"shadow":2,"hit_power":0,"id":4007,"atk_power":200,"hit_area":60,"skill_cancel_time":0.1,"width":100,"hit_rate":1.45,"name":"阿瑞斯","atk_script":"H007_normal_attack","height":230,"job":2,"bodytype":1.3,"hit_script":"hit_11"},"3007":{"path":"M008_output","img":"M008","skill":121,"actiontime":0.1,"speed":320,"skill_auto_script":"","next_skill":"S122_magic_M008_attack","skill_auto":0,"skill_script":"S121_magic_M008_attack","trail":0,"shadow":3,"hit_power":0,"id":3007,"atk_power":250,"hit_area":20,"skill_cancel_time":0.1,"width":150,"hit_rate":1.8,"name":"斯芬克斯","atk_script":"M008_normal_attack","height":210,"job":1,"bodytype":1.3,"hit_script":""},"4094":{"path":"H094_output","img":"H094","skill":0,"actiontime":1,"speed":220,"skill_auto_script":"","next_skill":"","skill_auto":0,"skill_script":"","trail":0,"shadow":1,"hit_power":0,"id":4094,"atk_power":200,"hit_area":40,"skill_cancel_time":0,"width":120,"hit_rate":1.45,"name":"人馬劍士","atk_script":"H094_normal_attack","height":230,"job":2,"bodytype":1.3,"hit_script":"hit_11"},"4023":{"path":"H023_output","img":"H023","skill":0,"actiontime":0.2,"speed":130,"skill_auto_script":"","next_skill":"","skill_auto":0,"skill_script":"","trail":1,"shadow":2,"hit_power":0,"id":4023,"atk_power":200,"hit_area":260,"skill_cancel_time":0,"width":80,"hit_rate":1.6,"name":"戈爾貢姐妹","atk_script":"H023_normal_attack","height":190,"job":3,"bodytype":1.3,"hit_script":"hit_31"},"3051":{"path":"M051_output","img":"M051","skill":0,"actiontime":1,"speed":220,"skill_auto_script":"","next_skill":"","skill_auto":0,"skill_script":"","trail":0,"shadow":1,"hit_power":0,"id":3051,"atk_power":250,"hit_area":40,"skill_cancel_time":0,"width":60,"hit_rate":1.45,"name":"刻耳柏洛斯","atk_script":"M051_normal_attack","height":200,"job":2,"bodytype":1.3,"hit_script":"hit_11"},"3105":{"path":"M022_output","img":"M105","skill":0,"actiontime":0.1,"speed":180,"skill_auto_script":"","next_skill":"","skill_auto":0,"skill_script":"","trail":0,"shadow":1,"hit_power":0,"id":3105,"atk_power":250,"hit_area":240,"skill_cancel_time":0,"width":100,"hit_rate":1.6,"name":"羊頭人弓手","atk_script":"M105_normal_attack","height":160,"job":2,"bodytype":1.3,"hit_script":"hit_11"},"4021":{"path":"H021_output","img":"H021","skill":201,"actiontime":0.2,"speed":200,"skill_auto_script":"H021_auto1_attack","next_skill":"S202_magic_H021_attack","skill_auto":601,"skill_script":"S201_magic_H021_attack","trail":0,"shadow":1,"hit_power":0,"id":4021,"atk_power":200,"hit_area":40,"skill_cancel_time":0.3,"width":100,"hit_rate":1.45,"name":"屠龍齊格飛","atk_script":"H021_normal_attack","height":200,"job":2,"bodytype":1.3,"hit_script":"hit_11"},"3024":{"path":"M024_output","img":"M024","skill":0,"actiontime":0.1,"speed":180,"skill_auto_script":"","next_skill":"","skill_auto":0,"skill_script":"","trail":0,"shadow":1,"hit_power":0,"id":3024,"atk_power":250,"hit_area":40,"skill_cancel_time":0,"width":80,"hit_rate":1.45,"name":"黑色羊頭武士","atk_script":"M024_normal_attack","height":160,"job":2,"bodytype":1.3,"hit_script":"hit_11"},"4018":{"path":"H018_output","img":"H018","skill":221,"actiontime":0.4,"speed":220,"skill_auto_script":"H018_auto1_attack","next_skill":"S222_magic_H018_attack","skill_auto":615,"skill_script":"S221_magic_H018_attack","trail":0,"shadow":2,"hit_power":0,"id":4018,"atk_power":200,"hit_area":50,"skill_cancel_time":0.2,"width":100,"hit_rate":1.45,"name":"索爾","atk_script":"H018_normal_attack","height":210,"job":2,"bodytype":1.3,"hit_script":"hit_11"},"4110":{"path":"H110_output","img":"H110","skill":301,"actiontime":0.3,"speed":180,"skill_auto_script":"H110_normal_attack","next_skill":"S302_magic_H110_attack","skill_auto":617,"skill_script":"S301_magic_H110_attack","trail":0,"shadow":1,"hit_power":0,"id":4110,"atk_power":200,"hit_area":280,"skill_cancel_time":0.3,"width":90,"hit_rate":1.6,"name":"塔瑞爾","atk_script":"H110_normal_attack","height":170,"job":3,"bodytype":1.3,"hit_script":"hit_31"},"4016":{"path":"H016_output","img":"H016","skill":411,"actiontime":0.2,"speed":180,"skill_auto_script":"H016_auto1_attack","next_skill":"S412_magic_H016_attack","skill_auto":609,"skill_script":"S411_magic_H016_attack","trail":1,"shadow":1,"hit_power":0,"id":4016,"atk_power":200,"hit_area":200,"skill_cancel_time":0.5,"width":60,"hit_rate":1.65,"name":"戰場女武神","atk_script":"H016_normal_attack","height":190,"job":4,"bodytype":1.3,"hit_script":"hit_42"},"4014":{"path":"H014_output","img":"H014","skill":111,"actiontime":0.2,"speed":210,"skill_auto_script":"H014_auto1_attack","next_skill":"S112_magic_H014_attack","skill_auto":612,"skill_script":"S111_magic_H014_attack","trail":0,"shadow":1,"hit_power":0,"id":4014,"atk_power":200,"hit_area":20,"skill_cancel_time":0.3,"width":90,"hit_rate":1.8,"name":"瓦爾基裡","atk_script":"H014_normal_attack","height":190,"job":1,"bodytype":1.3,"hit_script":"hit_11"},"3035":{"path":"M035_output","img":"M035","skill":0,"actiontime":0.2,"speed":220,"skill_auto_script":"","next_skill":"","skill_auto":0,"skill_script":"","trail":0,"shadow":1,"hit_power":0,"id":3035,"atk_power":250,"hit_area":40,"skill_cancel_time":0,"width":60,"hit_rate":1.45,"name":"小藍龍","atk_script":"M035_normal_attack","height":190,"job":2,"bodytype":1.3,"hit_script":"hit_11"},"4081":{"path":"H081_output","img":"H081","skill":201,"actiontime":1,"speed":200,"skill_auto_script":"H081_auto1_attack","next_skill":"S202_magic_H081_attack","skill_auto":617,"skill_script":"S201_magic_H081_attack","trail":0,"shadow":1,"hit_power":0,"id":4081,"atk_power":200,"hit_area":40,"skill_cancel_time":0,"width":85,"hit_rate":1.45,"name":"忒修斯","atk_script":"H081_normal_attack","height":200,"job":2,"bodytype":1.3,"hit_script":"hit_11"},"3081":{"path":"M081_output","img":"M081","skill":0,"actiontime":1,"speed":220,"skill_auto_script":"","next_skill":"","skill_auto":0,"skill_script":"","trail":0,"shadow":1,"hit_power":0,"id":3081,"atk_power":250,"hit_area":180,"skill_cancel_time":0,"width":80,"hit_rate":1.65,"name":"火巨人之王","atk_script":"M081_normal_attack","height":200,"job":2,"bodytype":1.3,"hit_script":"hit_11"},"3056":{"path":"M056_output","img":"M056","skill":0,"actiontime":1,"speed":220,"skill_auto_script":"","next_skill":"","skill_auto":0,"skill_script":"","trail":0,"shadow":1,"hit_power":0,"id":3056,"atk_power":250,"hit_area":40,"skill_cancel_time":0,"width":80,"hit_rate":1.45,"name":"深紅惡犬","atk_script":"M056_normal_attack","height":160,"job":2,"bodytype":1.3,"hit_script":"hit_11"},"4056":{"path":"H056_output","img":"H056","skill":0,"actiontime":0.3,"speed":160,"skill_auto_script":"","next_skill":"","skill_auto":0,"skill_script":"","trail":1,"shadow":1,"hit_power":0,"id":4056,"atk_power":200,"hit_area":250,"skill_cancel_time":0,"width":80,"hit_rate":1.6,"name":"精靈射手","atk_script":"H056_normal_attack","height":190,"job":3,"bodytype":1.3,"hit_script":"hit_31"},"3043":{"path":"M042_output","img":"M043","skill":0,"actiontime":1,"speed":100,"skill_auto_script":"","next_skill":"","skill_auto":0,"skill_script":"","trail":0,"shadow":1,"hit_power":0,"id":3043,"atk_power":250,"hit_area":40,"skill_cancel_time":0,"width":80,"hit_rate":1.45,"name":"地獄石像鬼","atk_script":"M043_normal_attack","height":200,"job":2,"bodytype":1.3,"hit_script":"hit_11"},"4104":{"path":"H104_output","img":"H104","skill":121,"actiontime":0.4,"speed":200,"skill_auto_script":"H104_auto1_attack","next_skill":"S122_magic_H104_attack","skill_auto":603,"skill_script":"S121_magic_H104_attack","trail":0,"shadow":1,"hit_power":0,"id":4104,"atk_power":200,"hit_area":20,"skill_cancel_time":0.3,"width":90,"hit_rate":1.8,"name":"斯巴達戰鬼","atk_script":"H104_normal_attack","height":220,"job":1,"bodytype":1.3,"hit_script":"hit_11"},"4086":{"path":"H086_output","img":"H086","skill":411,"actiontime":1,"speed":120,"skill_auto_script":"H086_normal_attack","next_skill":"S412_magic_H086_attack","skill_auto":616,"skill_script":"S411_magic_H086_attack","trail":0,"shadow":1,"hit_power":0,"id":4086,"atk_power":200,"hit_area":200,"skill_cancel_time":0,"width":75,"hit_rate":1.65,"name":"紅繆斯女神","atk_script":"H086_normal_attack","height":190,"job":4,"bodytype":1.3,"hit_script":"hit_11"},"3020":{"path":"M020_output","img":"M020","skill":221,"actiontime":1,"speed":33,"skill_auto_script":"","next_skill":"S222_magic_M020_attack","skill_auto":0,"skill_script":"S221_magic_M020_attack","trail":0,"shadow":2,"hit_power":0,"id":3020,"atk_power":250,"hit_area":40,"skill_cancel_time":221,"width":140,"hit_rate":1.8,"name":"重裝食人妖","atk_script":"M020_normal_attack","height":240,"job":1,"bodytype":1.3,"hit_script":"hit_11"},"4003":{"path":"H003_output","img":"H003","skill":401,"actiontime":0.4,"speed":150,"skill_auto_script":"H003_auto1_attack","next_skill":"S402_magic_H003_attack","skill_auto":607,"skill_script":"S401_magic_H003_attack","trail":0,"shadow":1,"hit_power":0,"id":4003,"atk_power":200,"hit_area":220,"skill_cancel_time":0.2,"width":80,"hit_rate":1.65,"name":"宙斯","atk_script":"H003_normal_attack","height":260,"job":4,"bodytype":1.2,"hit_script":"hit_41"},"3003":{"path":"M003_output","img":"M003","skill":0,"actiontime":0.2,"speed":30,"skill_auto_script":"","next_skill":"","skill_auto":0,"skill_script":"","trail":0,"shadow":1,"hit_power":0,"id":3003,"atk_power":250,"hit_area":40,"skill_cancel_time":0,"width":50,"hit_rate":1.45,"name":"藍色史萊姆","atk_script":"M003_normal_attack","height":90,"job":2,"bodytype":1.3,"hit_script":"hit_31"},"4046":{"path":"H046_output","img":"H046","skill":0,"actiontime":0.2,"speed":220,"skill_auto_script":"","next_skill":"","skill_auto":0,"skill_script":"","trail":0,"shadow":1,"hit_power":0,"id":4046,"atk_power":200,"hit_area":40,"skill_cancel_time":0,"width":80,"hit_rate":1.45,"name":"希臘精兵","atk_script":"H046_normal_attack","height":220,"job":2,"bodytype":1.3,"hit_script":"hit_11"},"3046":{"path":"M046_output","img":"M046","skill":0,"actiontime":0.2,"speed":220,"skill_auto_script":"","next_skill":"","skill_auto":0,"skill_script":"","trail":0,"shadow":1,"hit_power":0,"id":3046,"atk_power":250,"hit_area":40,"skill_cancel_time":0,"width":40,"hit_rate":1.45,"name":"褐色撕咬蝙蝠","atk_script":"M046_normal_attack","height":200,"job":2,"bodytype":1.3,"hit_script":"hit_11"},"3058":{"path":"M058_output","img":"M058","skill":0,"actiontime":1,"speed":220,"skill_auto_script":"","next_skill":"","skill_auto":0,"skill_script":"","trail":0,"shadow":1,"hit_power":0,"id":3058,"atk_power":250,"hit_area":40,"skill_cancel_time":0,"width":80,"hit_rate":1.45,"name":"座狼首領","atk_script":"M058_normal_attack","height":160,"job":2,"bodytype":1.3,"hit_script":"hit_11"},"3104":{"path":"M104_output","img":"M104","skill":412,"actiontime":0.1,"speed":160,"skill_auto_script":"","next_skill":"S412_magic_M104_attack","skill_auto":0,"skill_script":"S412_magic_M104_attack","trail":1,"shadow":2,"hit_power":0,"id":3104,"atk_power":250,"hit_area":40,"skill_cancel_time":0.1,"width":70,"hit_rate":1.45,"name":"真·法夫納","atk_script":"M104_normal_attack","height":300,"job":2,"bodytype":1,"hit_script":"hit_42"},"3099":{"path":"M099_output","img":"M099","skill":0,"actiontime":1,"speed":220,"skill_auto_script":"","next_skill":"","skill_auto":0,"skill_script":"","trail":0,"shadow":1,"hit_power":0,"id":3099,"atk_power":250,"hit_area":40,"skill_cancel_time":0,"width":60,"hit_rate":1.45,"name":"綠色塞壬之王","atk_script":"M099_normal_attack","height":160,"job":2,"bodytype":1.3,"hit_script":"hit_11"},"3032":{"path":"M032_output","img":"M032","skill":0,"actiontime":0.2,"speed":220,"skill_auto_script":"","next_skill":"","skill_auto":0,"skill_script":"","trail":0,"shadow":1,"hit_power":0,"id":3032,"atk_power":250,"hit_area":40,"skill_cancel_time":0,"width":100,"hit_rate":1.45,"name":"小紅龍","atk_script":"M032_normal_attack","height":190,"job":2,"bodytype":1.3,"hit_script":"hit_42"},"3059":{"path":"M059_output","img":"M059","skill":221,"actiontime":0.2,"speed":220,"skill_auto_script":"","next_skill":"S222_magic_M059_attack","skill_auto":0,"skill_script":"S221_magic_M059_attack","trail":0,"shadow":1,"hit_power":0,"id":3059,"atk_power":250,"hit_area":40,"skill_cancel_time":0.2,"width":80,"hit_rate":1.45,"name":"塔羅斯","atk_script":"M059_normal_attack","height":160,"job":2,"bodytype":1.3,"hit_script":"hit_11"},"4024":{"path":"H024_output","img":"H024","skill":0,"actiontime":0.2,"speed":130,"skill_auto_script":"","next_skill":"","skill_auto":0,"skill_script":"","trail":1,"shadow":2,"hit_power":0,"id":4024,"atk_power":200,"hit_area":260,"skill_cancel_time":0,"width":80,"hit_rate":1.6,"name":"憤怒戈爾貢","atk_script":"H024_normal_attack","height":190,"job":3,"bodytype":1.3,"hit_script":"hit_31"},"3025":{"path":"M024_output","img":"M025","skill":0,"actiontime":0.1,"speed":180,"skill_auto_script":"","next_skill":"","skill_auto":0,"skill_script":"","trail":0,"shadow":1,"hit_power":0,"id":3025,"atk_power":250,"hit_area":40,"skill_cancel_time":0,"width":100,"hit_rate":1.45,"name":"黑色羊頭戰士","atk_script":"M025_normal_attack","height":160,"job":2,"bodytype":1.3,"hit_script":"hit_11"},"3030":{"path":"M030_output","img":"M030","skill":422,"actiontime":0.1,"speed":160,"skill_auto_script":"","next_skill":"S422_magic_M030_attack","skill_auto":0,"skill_script":"S422_magic_M030_attack","trail":1,"shadow":2,"hit_power":0,"id":3030,"atk_power":250,"hit_area":280,"skill_cancel_time":0.1,"width":70,"hit_rate":1.65,"name":"藍龍","atk_script":"M030_normal_attack","height":300,"job":4,"bodytype":0.9,"hit_script":"hit_43"},"4030":{"path":"H030_output","img":"H030","skill":0,"actiontime":0.2,"speed":140,"skill_auto_script":"","next_skill":"","skill_auto":0,"skill_script":"","trail":1,"shadow":2,"hit_power":0,"id":4030,"atk_power":200,"hit_area":250,"skill_cancel_time":0,"width":120,"hit_rate":1.6,"name":"森林樹妖","atk_script":"H030_normal_attack","height":210,"job":3,"bodytype":1.3,"hit_script":"hit_31"},"3053":{"path":"M053_output","img":"M053","skill":0,"actiontime":1,"speed":220,"skill_auto_script":"","next_skill":"","skill_auto":0,"skill_script":"","trail":0,"shadow":1,"hit_power":0,"id":3053,"atk_power":250,"hit_area":40,"skill_cancel_time":0,"width":80,"hit_rate":1.45,"name":"芬裡爾","atk_script":"M053_normal_attack","height":160,"job":2,"bodytype":1.3,"hit_script":"hit_11"}}}